[{"responseTime": 1165.92031, "createdAt": "2015-07-12T00:01:38.030000", "endpointUrl": "https://api.onedrive.com/", "apiName": "OneDrive"}, {"responseTime": 1110.331581, "createdAt": "2015-07-12T00:03:42.149000", "endpointUrl": "https://api.onedrive.com/", "apiName": "OneDrive"}, {"responseTime": 1071.033341, "createdAt": "2015-07-12T00:05:43.227000", "endpointUrl": "https://api.onedrive.com/", "apiName": "OneDrive"}, {"responseTime": 1403.087108, "createdAt": "2015-07-12T00:09:09.665000", "endpointUrl": "https://api.onedrive.com/", "apiName": "OneDrive"}, {"responseTime": 1003.512941, "createdAt": "2015-07-12T00:13:17.210000", "endpointUrl": "https://api.onedrive.com/", "apiName": "OneDrive"}, {"responseTime": 1330.825602, "createdAt": "2015-07-12T00:15:27.150000", "endpointUrl": "https://api.onedrive.com/", "apiName": "OneDrive"}, {"responseTime": 1181.287584, "createdAt": "2015-07-12T00:17:52.008000", "endpointUrl": "https://api.onedrive.com/", "apiName": "OneDrive"}, {"responseTime": 1135.496321, "createdAt": "2015-07-12T00:20:23.921000", "endpointUrl": "https://api.onedrive.com/", "apiName": "OneDrive"}, {"responseTime": 999.57891, "createdAt": "2015-07-12T00:22:43.376000", "endpointUrl": "https://api.onedrive.com/", "apiName": "OneDrive"}, {"responseTime": 1119.611968, "createdAt": "2015-07-12T00:26:22.312000", "endpointUrl": "https://api.onedrive.com/", "apiName": "OneDrive"}, {"responseTime": 1639.13881, "createdAt": "2015-07-12T00:29:48.967000", "endpointUrl": "https://api.onedrive.com/", "apiName": "OneDrive"}, {"responseTime": 1556.40344, "createdAt": "2015-07-12T06:32:16.023000", "endpointUrl": "https://api.onedrive.com/", "apiName": "OneDrive"}, {"responseTime": 1813.097876, "createdAt": "2015-07-12T06:38:57.436000", "endpointUrl": "https://api.onedrive.com/", "apiName": "OneDrive"}, {"responseTime": 1397.660957, "createdAt": "2015-07-12T06:45:09.888000", "endpointUrl": "https://api.onedrive.com/", "apiName": "OneDrive"}, {"responseTime": 1286.776728, "createdAt": "2015-07-12T06:48:16.051000", "endpointUrl": "https://api.onedrive.com/", "apiName": "OneDrive"}, {"responseTime": 1462.329097, "createdAt": "2015-07-12T06:50:30.480000", "endpointUrl": "https://api.onedrive.com/", "apiName": "OneDrive"}, {"responseTime": 2039.012793, "createdAt": "2015-07-12T06:54:55.119000", "endpointUrl": "https://api.onedrive.com/", "apiName": "OneDrive"}, {"responseTime": 992.877964, "createdAt": "2015-07-12T06:57:00.399000", "endpointUrl": "https://api.onedrive.com/", "apiName": "OneDrive"}, {"responseTime": 1029.56971, "createdAt": "2015-07-12T06:59:14.813000", "endpointUrl": "https://api.onedrive.com/", "apiName": "OneDrive"}, {"responseTime": 1127.098789, "createdAt": "2015-07-12T07:01:21.253000", "endpointUrl": "https://api.onedrive.com/", "apiName": "OneDrive"}, {"responseTime": 1343.053251, "createdAt": "2015-07-12T07:03:30.455000", "endpointUrl": "https://api.onedrive.com/", "apiName": "OneDrive"}, {"responseTime": 2718.937459, "createdAt": "2015-07-12T07:12:31.161000", "endpointUrl": "https://api.onedrive.com/", "apiName": "OneDrive"}, {"responseTime": 1642.367426, "createdAt": "2015-07-12T07:15:15.043000", "endpointUrl": "https://api.onedrive.com/", "apiName": "OneDrive"}, {"responseTime": 5626.116934, "createdAt": "2015-07-12T07:17:27.906000", "endpointUrl": "https://api.onedrive.com/", "apiName": "OneDrive"}, {"responseTime": 4351.639156, "createdAt": "2015-07-12T07:19:58.545000", "endpointUrl": "https://api.onedrive.com/", "apiName": "OneDrive"}, {"responseTime": 1343.315423, "createdAt": "2015-07-12T07:24:18.115000", "endpointUrl": "https://api.onedrive.com/", "apiName": "OneDrive"}, {"responseTime": 1903.514644, "createdAt": "2015-07-12T07:29:39.127000", "endpointUrl": "https://api.onedrive.com/", "apiName": "OneDrive"}, {"responseTime": 1135.414856, "createdAt": "2015-07-12T11:32:10.788000", "endpointUrl": "https://api.onedrive.com/", "apiName": "OneDrive"}, {"responseTime": 1444.963196, "createdAt": "2015-07-12T11:35:03.287000", "endpointUrl": "https://api.onedrive.com/", "apiName": "OneDrive"}, {"responseTime": 1310.081223, "createdAt": "2015-07-12T11:44:18.033000", "endpointUrl": "https://api.onedrive.com/", "apiName": "OneDrive"}, {"responseTime": 1537.555945, "createdAt": "2015-07-12T11:46:48.838000", "endpointUrl": "https://api.onedrive.com/", "apiName": "OneDrive"}, {"responseTime": 1459.420547, "createdAt": "2015-07-12T11:50:08.146000", "endpointUrl": "https://api.onedrive.com/", "apiName": "OneDrive"}, {"responseTime": 1230.228942, "createdAt": "2015-07-12T11:52:34.225000", "endpointUrl": "https://api.onedrive.com/", "apiName": "OneDrive"}, {"responseTime": 1319.229199, "createdAt": "2015-07-12T11:54:53.926000", "endpointUrl": "https://api.onedrive.com/", "apiName": "OneDrive"}, {"responseTime": 1237.114, "createdAt": "2015-07-12T11:57:32.091000", "endpointUrl": "https://api.onedrive.com/", "apiName": "OneDrive"}, {"responseTime": 1394.591794, "createdAt": "2015-07-12T11:59:32.738000", "endpointUrl": "https://api.onedrive.com/", "apiName": "OneDrive"}, {"responseTime": 1236.025804, "createdAt": "2015-07-12T12:04:48.197000", "endpointUrl": "https://api.onedrive.com/", "apiName": "OneDrive"}, {"responseTime": 1495.157681, "createdAt": "2015-07-12T12:07:40.811000", "endpointUrl": "https://api.onedrive.com/", "apiName": "OneDrive"}, {"responseTime": 1109.10255, "createdAt": "2015-07-12T12:11:32.571000", "endpointUrl": "https://api.onedrive.com/", "apiName": "OneDrive"}, {"responseTime": 2002.937113, "createdAt": "2015-07-12T12:15:01.718000", "endpointUrl": "https://api.onedrive.com/", "apiName": "OneDrive"}, {"responseTime": 1037.994583, "createdAt": "2015-07-12T12:17:12.653000", "endpointUrl": "https://api.onedrive.com/", "apiName": "OneDrive"}, {"responseTime": 1286.475479, "createdAt": "2015-07-12T12:20:33.829000", "endpointUrl": "https://api.onedrive.com/", "apiName": "OneDrive"}, {"responseTime": 1482.16744, "createdAt": "2015-07-12T12:24:05.308000", "endpointUrl": "https://api.onedrive.com/", "apiName": "OneDrive"}, {"responseTime": 1300.375464, "createdAt": "2015-07-12T12:26:30.155000", "endpointUrl": "https://api.onedrive.com/", "apiName": "OneDrive"}, {"responseTime": 1117.063122, "createdAt": "2015-07-12T12:28:53.743000", "endpointUrl": "https://api.onedrive.com/", "apiName": "OneDrive"}, {"responseTime": 2415.728446, "createdAt": "2015-07-12T23:35:43.918000", "endpointUrl": "https://api.onedrive.com/", "apiName": "OneDrive"}, {"responseTime": 1409.994922, "createdAt": "2015-07-12T23:39:33.892000", "endpointUrl": "https://api.onedrive.com/", "apiName": "OneDrive"}, {"responseTime": 1213.986174, "createdAt": "2015-07-12T23:42:07.631000", "endpointUrl": "https://api.onedrive.com/", "apiName": "OneDrive"}, {"responseTime": 1348.71004, "createdAt": "2015-07-12T23:46:17.808000", "endpointUrl": "https://api.onedrive.com/", "apiName": "OneDrive"}, {"responseTime": 1556.973132, "createdAt": "2015-07-12T23:50:20.725000", "endpointUrl": "https://api.onedrive.com/", "apiName": "OneDrive"}, {"responseTime": 1350.517421, "createdAt": "2015-07-12T23:53:52.229000", "endpointUrl": "https://api.onedrive.com/", "apiName": "OneDrive"}, {"responseTime": 782.826324, "createdAt": "2015-07-12T23:56:00.455000", "endpointUrl": "https://api.onedrive.com/", "apiName": "OneDrive"}, {"responseTime": 1120.498781, "createdAt": "2015-07-12T23:58:58.763000", "endpointUrl": "https://api.onedrive.com/", "apiName": "OneDrive"}, {"responseTime": 1068.347823, "createdAt": "2015-07-13T00:02:26.756000", "endpointUrl": "https://api.onedrive.com/", "apiName": "OneDrive"}, {"responseTime": 786.610782, "createdAt": "2015-07-13T00:05:08.638000", "endpointUrl": "https://api.onedrive.com/", "apiName": "OneDrive"}, {"responseTime": 1385.455958, "createdAt": "2015-07-13T00:09:40.711000", "endpointUrl": "https://api.onedrive.com/", "apiName": "OneDrive"}, {"responseTime": 1078.954978, "createdAt": "2015-07-13T00:12:53.453000", "endpointUrl": "https://api.onedrive.com/", "apiName": "OneDrive"}, {"responseTime": 1106.185428, "createdAt": "2015-07-13T00:15:19.289000", "endpointUrl": "https://api.onedrive.com/", "apiName": "OneDrive"}, {"responseTime": 814.172878, "createdAt": "2015-07-13T00:17:36.438000", "endpointUrl": "https://api.onedrive.com/", "apiName": "OneDrive"}, {"responseTime": 1064.602722, "createdAt": "2015-07-13T00:19:52.055000", "endpointUrl": "https://api.onedrive.com/", "apiName": "OneDrive"}, {"responseTime": 1265.815531, "createdAt": "2015-07-13T00:23:51.842000", "endpointUrl": "https://api.onedrive.com/", "apiName": "OneDrive"}, {"responseTime": 1305.548331, "createdAt": "2015-07-13T00:26:49.559000", "endpointUrl": "https://api.onedrive.com/", "apiName": "OneDrive"}, {"responseTime": 1208.77734, "createdAt": "2015-07-13T00:28:50.055000", "endpointUrl": "https://api.onedrive.com/", "apiName": "OneDrive"}, {"responseTime": 1692.584052, "createdAt": "2015-07-13T06:30:52.192000", "endpointUrl": "https://api.onedrive.com/", "apiName": "OneDrive"}, {"responseTime": 1279.417978, "createdAt": "2015-07-13T06:33:04.047000", "endpointUrl": "https://api.onedrive.com/", "apiName": "OneDrive"}, {"responseTime": 1703.910959, "createdAt": "2015-07-13T06:35:17.421000", "endpointUrl": "https://api.onedrive.com/", "apiName": "OneDrive"}, {"responseTime": 1223.653679, "createdAt": "2015-07-13T06:37:41.341000", "endpointUrl": "https://api.onedrive.com/", "apiName": "OneDrive"}, {"responseTime": 1077.655858, "createdAt": "2015-07-13T06:41:37.123000", "endpointUrl": "https://api.onedrive.com/", "apiName": "OneDrive"}, {"responseTime": 1298.69215, "createdAt": "2015-07-13T06:44:59.344000", "endpointUrl": "https://api.onedrive.com/", "apiName": "OneDrive"}, {"responseTime": 1163.617277, "createdAt": "2015-07-13T06:49:44.717000", "endpointUrl": "https://api.onedrive.com/", "apiName": "OneDrive"}, {"responseTime": 1551.615036, "createdAt": "2015-07-13T06:53:13.234000", "endpointUrl": "https://api.onedrive.com/", "apiName": "OneDrive"}, {"responseTime": 1362.361119, "createdAt": "2015-07-13T06:56:21.025000", "endpointUrl": "https://api.onedrive.com/", "apiName": "OneDrive"}, {"responseTime": 1201.673311, "createdAt": "2015-07-13T07:00:54.964000", "endpointUrl": "https://api.onedrive.com/", "apiName": "OneDrive"}, {"responseTime": 1288.74535, "createdAt": "2015-07-13T07:04:24.826000", "endpointUrl": "https://api.onedrive.com/", "apiName": "OneDrive"}, {"responseTime": 1506.959121, "createdAt": "2015-07-13T07:07:38.795000", "endpointUrl": "https://api.onedrive.com/", "apiName": "OneDrive"}, {"responseTime": 1484.31933, "createdAt": "2015-07-13T07:12:16.085000", "endpointUrl": "https://api.onedrive.com/", "apiName": "OneDrive"}, {"responseTime": 1296.44326, "createdAt": "2015-07-13T07:14:39.695000", "endpointUrl": "https://api.onedrive.com/", "apiName": "OneDrive"}, {"responseTime": 1291.656397, "createdAt": "2015-07-13T07:18:35.400000", "endpointUrl": "https://api.onedrive.com/", "apiName": "OneDrive"}, {"responseTime": 1292.667112, "createdAt": "2015-07-13T07:21:50.180000", "endpointUrl": "https://api.onedrive.com/", "apiName": "OneDrive"}, {"responseTime": 2207.534809, "createdAt": "2015-07-13T07:25:58.656000", "endpointUrl": "https://api.onedrive.com/", "apiName": "OneDrive"}, {"responseTime": 1581.04103, "createdAt": "2015-07-13T07:28:21.704000", "endpointUrl": "https://api.onedrive.com/", "apiName": "OneDrive"}, {"responseTime": 1467.493426, "createdAt": "2015-07-13T11:35:26.639000", "endpointUrl": "https://api.onedrive.com/", "apiName": "OneDrive"}, {"responseTime": 1309.480432, "createdAt": "2015-07-13T11:39:15.490000", "endpointUrl": "https://api.onedrive.com/", "apiName": "OneDrive"}, {"responseTime": 1548.191644, "createdAt": "2015-07-13T11:41:20.375000", "endpointUrl": "https://api.onedrive.com/", "apiName": "OneDrive"}, {"responseTime": 1174.035384, "createdAt": "2015-07-13T11:43:21.433000", "endpointUrl": "https://api.onedrive.com/", "apiName": "OneDrive"}, {"responseTime": 1174.264128, "createdAt": "2015-07-13T11:45:47.216000", "endpointUrl": "https://api.onedrive.com/", "apiName": "OneDrive"}, {"responseTime": 1406.158952, "createdAt": "2015-07-13T11:48:32.595000", "endpointUrl": "https://api.onedrive.com/", "apiName": "OneDrive"}, {"responseTime": 1515.621118, "createdAt": "2015-07-13T11:52:46.244000", "endpointUrl": "https://api.onedrive.com/", "apiName": "OneDrive"}, {"responseTime": 1290.937419, "createdAt": "2015-07-13T11:58:04.410000", "endpointUrl": "https://api.onedrive.com/", "apiName": "OneDrive"}, {"responseTime": 1265.636648, "createdAt": "2015-07-13T12:00:13.403000", "endpointUrl": "https://api.onedrive.com/", "apiName": "OneDrive"}, {"responseTime": 1130.6308, "createdAt": "2015-07-13T12:06:06.612000", "endpointUrl": "https://api.onedrive.com/", "apiName": "OneDrive"}, {"responseTime": 1327.573615, "createdAt": "2015-07-13T12:08:07.199000", "endpointUrl": "https://api.onedrive.com/", "apiName": "OneDrive"}, {"responseTime": 1236.148587, "createdAt": "2015-07-13T12:10:33.481000", "endpointUrl": "https://api.onedrive.com/", "apiName": "OneDrive"}, {"responseTime": 1172.492757, "createdAt": "2015-07-13T12:15:05.088000", "endpointUrl": "https://api.onedrive.com/", "apiName": "OneDrive"}, {"responseTime": 1443.921719, "createdAt": "2015-07-13T12:19:34.659000", "endpointUrl": "https://api.onedrive.com/", "apiName": "OneDrive"}, {"responseTime": 1398.25799, "createdAt": "2015-07-13T12:23:31.389000", "endpointUrl": "https://api.onedrive.com/", "apiName": "OneDrive"}, {"responseTime": 2088.229798, "createdAt": "2015-07-13T12:25:40.982000", "endpointUrl": "https://api.onedrive.com/", "apiName": "OneDrive"}, {"responseTime": 1448.80099, "createdAt": "2015-07-13T12:27:52.573000", "endpointUrl": "https://api.onedrive.com/", "apiName": "OneDrive"}, {"responseTime": 3578.944726, "createdAt": "2015-07-13T12:31:24.360000", "endpointUrl": "https://api.onedrive.com/", "apiName": "OneDrive"}, {"responseTime": 1595.411535, "createdAt": "2015-07-13T23:32:12.719000", "endpointUrl": "https://api.onedrive.com/", "apiName": "OneDrive"}, {"responseTime": 1107.637696, "createdAt": "2015-07-13T23:35:06.521000", "endpointUrl": "https://api.onedrive.com/", "apiName": "OneDrive"}, {"responseTime": 998.667347, "createdAt": "2015-07-13T23:37:44.683000", "endpointUrl": "https://api.onedrive.com/", "apiName": "OneDrive"}, {"responseTime": 1006.444894, "createdAt": "2015-07-13T23:39:56.266000", "endpointUrl": "https://api.onedrive.com/", "apiName": "OneDrive"}, {"responseTime": 1113.466533, "createdAt": "2015-07-13T23:43:26.460000", "endpointUrl": "https://api.onedrive.com/", "apiName": "OneDrive"}, {"responseTime": 970.574826, "createdAt": "2015-07-13T23:45:37.894000", "endpointUrl": "https://api.onedrive.com/", "apiName": "OneDrive"}, {"responseTime": 1116.146414, "createdAt": "2015-07-13T23:47:38.219000", "endpointUrl": "https://api.onedrive.com/", "apiName": "OneDrive"}, {"responseTime": 1159.024852, "createdAt": "2015-07-13T23:51:18.817000", "endpointUrl": "https://api.onedrive.com/", "apiName": "OneDrive"}, {"responseTime": 1219.062233, "createdAt": "2015-07-13T23:53:57.429000", "endpointUrl": "https://api.onedrive.com/", "apiName": "OneDrive"}, {"responseTime": 1054.937749, "createdAt": "2015-07-13T23:57:07.059000", "endpointUrl": "https://api.onedrive.com/", "apiName": "OneDrive"}, {"responseTime": 1036.291608, "createdAt": "2015-07-14T00:01:11.441000", "endpointUrl": "https://api.onedrive.com/", "apiName": "OneDrive"}, {"responseTime": 745.339164, "createdAt": "2015-07-14T00:04:13.255000", "endpointUrl": "https://api.onedrive.com/", "apiName": "OneDrive"}, {"responseTime": 1243.236455, "createdAt": "2015-07-14T00:07:05.016000", "endpointUrl": "https://api.onedrive.com/", "apiName": "OneDrive"}, {"responseTime": 1174.659895, "createdAt": "2015-07-14T00:09:11.267000", "endpointUrl": "https://api.onedrive.com/", "apiName": "OneDrive"}, {"responseTime": 1948.762253, "createdAt": "2015-07-14T00:11:18.259000", "endpointUrl": "https://api.onedrive.com/", "apiName": "OneDrive"}, {"responseTime": 1106.671194, "createdAt": "2015-07-14T00:14:47.603000", "endpointUrl": "https://api.onedrive.com/", "apiName": "OneDrive"}, {"responseTime": 1075.140312, "createdAt": "2015-07-14T00:18:27.055000", "endpointUrl": "https://api.onedrive.com/", "apiName": "OneDrive"}, {"responseTime": 1031.156465, "createdAt": "2015-07-14T00:21:22.127000", "endpointUrl": "https://api.onedrive.com/", "apiName": "OneDrive"}, {"responseTime": 1965.079243, "createdAt": "2015-07-14T00:23:53.038000", "endpointUrl": "https://api.onedrive.com/", "apiName": "OneDrive"}, {"responseTime": 1591.521927, "createdAt": "2015-07-14T00:30:33.461000", "endpointUrl": "https://api.onedrive.com/", "apiName": "OneDrive"}, {"responseTime": 1217.830898, "createdAt": "2015-07-14T06:31:20.344000", "endpointUrl": "https://api.onedrive.com/", "apiName": "OneDrive"}, {"responseTime": 1419.141308, "createdAt": "2015-07-14T06:33:20.951000", "endpointUrl": "https://api.onedrive.com/", "apiName": "OneDrive"}, {"responseTime": 1291.542934, "createdAt": "2015-07-14T06:35:46.730000", "endpointUrl": "https://api.onedrive.com/", "apiName": "OneDrive"}, {"responseTime": 5510.91742, "createdAt": "2015-07-14T06:39:19.400000", "endpointUrl": "https://api.onedrive.com/", "apiName": "OneDrive"}, {"responseTime": 1246.303614, "createdAt": "2015-07-14T06:41:28.796000", "endpointUrl": "https://api.onedrive.com/", "apiName": "OneDrive"}, {"responseTime": 1137.810017, "createdAt": "2015-07-14T06:44:23.874000", "endpointUrl": "https://api.onedrive.com/", "apiName": "OneDrive"}, {"responseTime": 1275.048635, "createdAt": "2015-07-14T06:47:13.777000", "endpointUrl": "https://api.onedrive.com/", "apiName": "OneDrive"}, {"responseTime": 1231.912896, "createdAt": "2015-07-14T06:50:15.066000", "endpointUrl": "https://api.onedrive.com/", "apiName": "OneDrive"}, {"responseTime": 1337.347915, "createdAt": "2015-07-14T06:52:38.915000", "endpointUrl": "https://api.onedrive.com/", "apiName": "OneDrive"}, {"responseTime": 1354.177159, "createdAt": "2015-07-14T06:55:11.546000", "endpointUrl": "https://api.onedrive.com/", "apiName": "OneDrive"}, {"responseTime": 1128.253426, "createdAt": "2015-07-14T06:58:12.670000", "endpointUrl": "https://api.onedrive.com/", "apiName": "OneDrive"}, {"responseTime": 1147.771638, "createdAt": "2015-07-14T07:00:29.203000", "endpointUrl": "https://api.onedrive.com/", "apiName": "OneDrive"}, {"responseTime": 1568.135517, "createdAt": "2015-07-14T07:04:41.568000", "endpointUrl": "https://api.onedrive.com/", "apiName": "OneDrive"}, {"responseTime": 1142.966521, "createdAt": "2015-07-14T07:08:15.151000", "endpointUrl": "https://api.onedrive.com/", "apiName": "OneDrive"}, {"responseTime": 3028.513926, "createdAt": "2015-07-14T07:11:22.581000", "endpointUrl": "https://api.onedrive.com/", "apiName": "OneDrive"}, {"responseTime": 1237.851203, "createdAt": "2015-07-14T07:13:29.567000", "endpointUrl": "https://api.onedrive.com/", "apiName": "OneDrive"}, {"responseTime": 973.522218, "createdAt": "2015-07-14T07:15:44.469000", "endpointUrl": "https://api.onedrive.com/", "apiName": "OneDrive"}, {"responseTime": 1395.088574, "createdAt": "2015-07-14T07:17:45.499000", "endpointUrl": "https://api.onedrive.com/", "apiName": "OneDrive"}, {"responseTime": 1582.214602, "createdAt": "2015-07-14T07:20:15.296000", "endpointUrl": "https://api.onedrive.com/", "apiName": "OneDrive"}, {"responseTime": 17914.48774, "createdAt": "2015-07-14T07:22:28.119000", "endpointUrl": "https://api.onedrive.com/", "apiName": "OneDrive"}, {"responseTime": 1427.381991, "createdAt": "2015-07-14T07:27:05.827000", "endpointUrl": "https://api.onedrive.com/", "apiName": "OneDrive"}, {"responseTime": 1256.521648, "createdAt": "2015-07-14T07:30:34.625000", "endpointUrl": "https://api.onedrive.com/", "apiName": "OneDrive"}, {"responseTime": 1263.315808, "createdAt": "2015-07-14T11:32:59.889000", "endpointUrl": "https://api.onedrive.com/", "apiName": "OneDrive"}, {"responseTime": 977.201325, "createdAt": "2015-07-14T11:35:04.512000", "endpointUrl": "https://api.onedrive.com/", "apiName": "OneDrive"}, {"responseTime": 1446.895689, "createdAt": "2015-07-14T11:40:39.653000", "endpointUrl": "https://api.onedrive.com/", "apiName": "OneDrive"}, {"responseTime": 1728.341474, "createdAt": "2015-07-14T11:44:16.303000", "endpointUrl": "https://api.onedrive.com/", "apiName": "OneDrive"}, {"responseTime": 1004.649101, "createdAt": "2015-07-14T11:46:33.092000", "endpointUrl": "https://api.onedrive.com/", "apiName": "OneDrive"}, {"responseTime": 1748.465639, "createdAt": "2015-07-14T11:50:01.395000", "endpointUrl": "https://api.onedrive.com/", "apiName": "OneDrive"}, {"responseTime": 1275.71261, "createdAt": "2015-07-14T11:53:29.912000", "endpointUrl": "https://api.onedrive.com/", "apiName": "OneDrive"}, {"responseTime": 1267.991494, "createdAt": "2015-07-14T11:55:33.399000", "endpointUrl": "https://api.onedrive.com/", "apiName": "OneDrive"}, {"responseTime": 1178.529518, "createdAt": "2015-07-14T12:00:46.900000", "endpointUrl": "https://api.onedrive.com/", "apiName": "OneDrive"}, {"responseTime": 961.639598, "createdAt": "2015-07-14T12:03:44.994000", "endpointUrl": "https://api.onedrive.com/", "apiName": "OneDrive"}, {"responseTime": 1445.26595, "createdAt": "2015-07-14T12:07:06.449000", "endpointUrl": "https://api.onedrive.com/", "apiName": "OneDrive"}, {"responseTime": 1072.087745, "createdAt": "2015-07-14T12:11:21.314000", "endpointUrl": "https://api.onedrive.com/", "apiName": "OneDrive"}, {"responseTime": 1019.91735, "createdAt": "2015-07-14T12:13:23.489000", "endpointUrl": "https://api.onedrive.com/", "apiName": "OneDrive"}, {"responseTime": 1339.059692, "createdAt": "2015-07-14T12:15:24.474000", "endpointUrl": "https://api.onedrive.com/", "apiName": "OneDrive"}, {"responseTime": 1487.429905, "createdAt": "2015-07-14T12:19:19.715000", "endpointUrl": "https://api.onedrive.com/", "apiName": "OneDrive"}, {"responseTime": 1437.549736, "createdAt": "2015-07-14T12:23:58.836000", "endpointUrl": "https://api.onedrive.com/", "apiName": "OneDrive"}, {"responseTime": 1198.114943, "createdAt": "2015-07-14T12:31:17.784000", "endpointUrl": "https://api.onedrive.com/", "apiName": "OneDrive"}, {"responseTime": 1150.08803, "createdAt": "2015-07-14T23:35:43.438000", "endpointUrl": "https://api.onedrive.com/", "apiName": "OneDrive"}, {"responseTime": 1168.990111, "createdAt": "2015-07-14T23:38:26.823000", "endpointUrl": "https://api.onedrive.com/", "apiName": "OneDrive"}, {"responseTime": 1085.948064, "createdAt": "2015-07-14T23:40:47.039000", "endpointUrl": "https://api.onedrive.com/", "apiName": "OneDrive"}, {"responseTime": 1504.473099, "createdAt": "2015-07-14T23:45:06.741000", "endpointUrl": "https://api.onedrive.com/", "apiName": "OneDrive"}, {"responseTime": 1096.526221, "createdAt": "2015-07-14T23:48:21.827000", "endpointUrl": "https://api.onedrive.com/", "apiName": "OneDrive"}, {"responseTime": 1434.482956, "createdAt": "2015-07-14T23:51:43.964000", "endpointUrl": "https://api.onedrive.com/", "apiName": "OneDrive"}, {"responseTime": 1138.255823, "createdAt": "2015-07-14T23:56:19.130000", "endpointUrl": "https://api.onedrive.com/", "apiName": "OneDrive"}, {"responseTime": 994.506207, "createdAt": "2015-07-14T23:58:43.554000", "endpointUrl": "https://api.onedrive.com/", "apiName": "OneDrive"}, {"responseTime": 1202.587364, "createdAt": "2015-07-15T00:08:34.902000", "endpointUrl": "https://api.onedrive.com/", "apiName": "OneDrive"}, {"responseTime": 1779.193304, "createdAt": "2015-07-15T00:10:37.354000", "endpointUrl": "https://api.onedrive.com/", "apiName": "OneDrive"}, {"responseTime": 1181.018637, "createdAt": "2015-07-15T00:14:08.096000", "endpointUrl": "https://api.onedrive.com/", "apiName": "OneDrive"}, {"responseTime": 1274.186088, "createdAt": "2015-07-15T00:17:58.204000", "endpointUrl": "https://api.onedrive.com/", "apiName": "OneDrive"}, {"responseTime": 1385.151769, "createdAt": "2015-07-15T00:21:12.305000", "endpointUrl": "https://api.onedrive.com/", "apiName": "OneDrive"}, {"responseTime": 2762.751558, "createdAt": "2015-07-15T00:30:39.816000", "endpointUrl": "https://api.onedrive.com/", "apiName": "OneDrive"}, {"responseTime": 1434.926773, "createdAt": "2015-07-15T06:32:53.433000", "endpointUrl": "https://api.onedrive.com/", "apiName": "OneDrive"}, {"responseTime": 925.056836, "createdAt": "2015-07-15T06:35:00.064000", "endpointUrl": "https://api.onedrive.com/", "apiName": "OneDrive"}, {"responseTime": 1231.780265, "createdAt": "2015-07-15T06:38:40.538000", "endpointUrl": "https://api.onedrive.com/", "apiName": "OneDrive"}, {"responseTime": 2274.12413, "createdAt": "2015-07-15T06:43:55.735000", "endpointUrl": "https://api.onedrive.com/", "apiName": "OneDrive"}, {"responseTime": 1424.429698, "createdAt": "2015-07-15T06:46:03.395000", "endpointUrl": "https://api.onedrive.com/", "apiName": "OneDrive"}, {"responseTime": 1051.815705, "createdAt": "2015-07-15T06:48:25.952000", "endpointUrl": "https://api.onedrive.com/", "apiName": "OneDrive"}, {"responseTime": 1035.490968, "createdAt": "2015-07-15T06:51:05.187000", "endpointUrl": "https://api.onedrive.com/", "apiName": "OneDrive"}, {"responseTime": 1401.35473, "createdAt": "2015-07-15T06:55:52.470000", "endpointUrl": "https://api.onedrive.com/", "apiName": "OneDrive"}, {"responseTime": 1508.598656, "createdAt": "2015-07-15T06:58:11.513000", "endpointUrl": "https://api.onedrive.com/", "apiName": "OneDrive"}, {"responseTime": 1234.354883, "createdAt": "2015-07-15T07:00:29.093000", "endpointUrl": "https://api.onedrive.com/", "apiName": "OneDrive"}, {"responseTime": 1231.887789, "createdAt": "2015-07-15T07:02:59.431000", "endpointUrl": "https://api.onedrive.com/", "apiName": "OneDrive"}, {"responseTime": 1086.580983, "createdAt": "2015-07-15T07:08:55.945000", "endpointUrl": "https://api.onedrive.com/", "apiName": "OneDrive"}, {"responseTime": 1151.517776, "createdAt": "2015-07-15T07:11:51.098000", "endpointUrl": "https://api.onedrive.com/", "apiName": "OneDrive"}, {"responseTime": 1461.098609, "createdAt": "2015-07-15T07:16:06.810000", "endpointUrl": "https://api.onedrive.com/", "apiName": "OneDrive"}, {"responseTime": 1551.782951, "createdAt": "2015-07-15T07:22:36.027000", "endpointUrl": "https://api.onedrive.com/", "apiName": "OneDrive"}, {"responseTime": 1460.243467, "createdAt": "2015-07-15T07:25:25.360000", "endpointUrl": "https://api.onedrive.com/", "apiName": "OneDrive"}, {"responseTime": 1393.023961, "createdAt": "2015-07-15T07:27:33.921000", "endpointUrl": "https://api.onedrive.com/", "apiName": "OneDrive"}, {"responseTime": 1497.657696, "createdAt": "2015-07-15T07:30:12.528000", "endpointUrl": "https://api.onedrive.com/", "apiName": "OneDrive"}, {"responseTime": 1328.463965, "createdAt": "2015-07-15T11:32:55.487000", "endpointUrl": "https://api.onedrive.com/", "apiName": "OneDrive"}, {"responseTime": 1036.139201, "createdAt": "2015-07-15T11:34:56.580000", "endpointUrl": "https://api.onedrive.com/", "apiName": "OneDrive"}, {"responseTime": 2238.155391, "createdAt": "2015-07-15T11:37:05.393000", "endpointUrl": "https://api.onedrive.com/", "apiName": "OneDrive"}, {"responseTime": 1466.116244, "createdAt": "2015-07-15T11:39:16.385000", "endpointUrl": "https://api.onedrive.com/", "apiName": "OneDrive"}, {"responseTime": 1004.995079, "createdAt": "2015-07-15T11:42:03.806000", "endpointUrl": "https://api.onedrive.com/", "apiName": "OneDrive"}, {"responseTime": 1921.466553, "createdAt": "2015-07-15T11:48:35.539000", "endpointUrl": "https://api.onedrive.com/", "apiName": "OneDrive"}, {"responseTime": 1220.835818, "createdAt": "2015-07-15T11:52:25.047000", "endpointUrl": "https://api.onedrive.com/", "apiName": "OneDrive"}, {"responseTime": 1720.283704, "createdAt": "2015-07-15T11:57:12.923000", "endpointUrl": "https://api.onedrive.com/", "apiName": "OneDrive"}, {"responseTime": 1542.706236, "createdAt": "2015-07-15T12:02:14.462000", "endpointUrl": "https://api.onedrive.com/", "apiName": "OneDrive"}, {"responseTime": 1793.188056, "createdAt": "2015-07-15T12:05:06.909000", "endpointUrl": "https://api.onedrive.com/", "apiName": "OneDrive"}, {"responseTime": 1425.944157, "createdAt": "2015-07-15T12:09:18.206000", "endpointUrl": "https://api.onedrive.com/", "apiName": "OneDrive"}, {"responseTime": 1032.104725, "createdAt": "2015-07-15T12:12:18.426000", "endpointUrl": "https://api.onedrive.com/", "apiName": "OneDrive"}, {"responseTime": 1115.025517, "createdAt": "2015-07-15T12:15:32.378000", "endpointUrl": "https://api.onedrive.com/", "apiName": "OneDrive"}, {"responseTime": 2574.010194, "createdAt": "2015-07-15T12:19:20.968000", "endpointUrl": "https://api.onedrive.com/", "apiName": "OneDrive"}, {"responseTime": 2380.146442, "createdAt": "2015-07-15T12:21:42.666000", "endpointUrl": "https://api.onedrive.com/", "apiName": "OneDrive"}, {"responseTime": 1643.97012, "createdAt": "2015-07-15T12:28:54.601000", "endpointUrl": "https://api.onedrive.com/", "apiName": "OneDrive"}, {"responseTime": 1246.13495, "createdAt": "2015-07-15T23:39:02.531000", "endpointUrl": "https://api.onedrive.com/", "apiName": "OneDrive"}, {"responseTime": 1168.502162, "createdAt": "2015-07-15T23:42:12.076000", "endpointUrl": "https://api.onedrive.com/", "apiName": "OneDrive"}, {"responseTime": 1079.754997, "createdAt": "2015-07-15T23:44:33.880000", "endpointUrl": "https://api.onedrive.com/", "apiName": "OneDrive"}, {"responseTime": 1256.220613, "createdAt": "2015-07-15T23:47:51.597000", "endpointUrl": "https://api.onedrive.com/", "apiName": "OneDrive"}, {"responseTime": 995.279155, "createdAt": "2015-07-15T23:50:39.292000", "endpointUrl": "https://api.onedrive.com/", "apiName": "OneDrive"}, {"responseTime": 1294.820637, "createdAt": "2015-07-15T23:55:50.885000", "endpointUrl": "https://api.onedrive.com/", "apiName": "OneDrive"}, {"responseTime": 986.753859, "createdAt": "2015-07-15T23:58:31.355000", "endpointUrl": "https://api.onedrive.com/", "apiName": "OneDrive"}, {"responseTime": 1280.86205, "createdAt": "2015-07-16T00:00:56.286000", "endpointUrl": "https://api.onedrive.com/", "apiName": "OneDrive"}, {"responseTime": 1138.230808, "createdAt": "2015-07-16T00:03:13.839000", "endpointUrl": "https://api.onedrive.com/", "apiName": "OneDrive"}, {"responseTime": 1312.553437, "createdAt": "2015-07-16T00:06:07.612000", "endpointUrl": "https://api.onedrive.com/", "apiName": "OneDrive"}, {"responseTime": 1597.026907, "createdAt": "2015-07-16T00:08:09.576000", "endpointUrl": "https://api.onedrive.com/", "apiName": "OneDrive"}, {"responseTime": 1056.661011, "createdAt": "2015-07-16T00:11:30.493000", "endpointUrl": "https://api.onedrive.com/", "apiName": "OneDrive"}, {"responseTime": 961.191953, "createdAt": "2015-07-16T00:13:35.285000", "endpointUrl": "https://api.onedrive.com/", "apiName": "OneDrive"}, {"responseTime": 958.473083, "createdAt": "2015-07-16T00:16:02.370000", "endpointUrl": "https://api.onedrive.com/", "apiName": "OneDrive"}, {"responseTime": 1302.911529, "createdAt": "2015-07-16T00:23:16.436000", "endpointUrl": "https://api.onedrive.com/", "apiName": "OneDrive"}, {"responseTime": 1070.02455, "createdAt": "2015-07-16T00:25:51.053000", "endpointUrl": "https://api.onedrive.com/", "apiName": "OneDrive"}, {"responseTime": 1268.642931, "createdAt": "2015-07-16T00:30:55.993000", "endpointUrl": "https://api.onedrive.com/", "apiName": "OneDrive"}, {"responseTime": 1223.397071, "createdAt": "2015-07-16T06:35:34.318000", "endpointUrl": "https://api.onedrive.com/", "apiName": "OneDrive"}, {"responseTime": 865.493042, "createdAt": "2015-07-16T06:37:44.416000", "endpointUrl": "https://api.onedrive.com/", "apiName": "OneDrive"}, {"responseTime": 924.410872, "createdAt": "2015-07-16T06:39:45.558000", "endpointUrl": "https://api.onedrive.com/", "apiName": "OneDrive"}, {"responseTime": 1087.988064, "createdAt": "2015-07-16T06:42:15.567000", "endpointUrl": "https://api.onedrive.com/", "apiName": "OneDrive"}, {"responseTime": 1211.603558, "createdAt": "2015-07-16T06:45:53.841000", "endpointUrl": "https://api.onedrive.com/", "apiName": "OneDrive"}, {"responseTime": 1274.912705, "createdAt": "2015-07-16T06:49:40.114000", "endpointUrl": "https://api.onedrive.com/", "apiName": "OneDrive"}, {"responseTime": 1093.738213, "createdAt": "2015-07-16T06:53:50.169000", "endpointUrl": "https://api.onedrive.com/", "apiName": "OneDrive"}, {"responseTime": 1482.09189, "createdAt": "2015-07-16T06:57:22.401000", "endpointUrl": "https://api.onedrive.com/", "apiName": "OneDrive"}, {"responseTime": 1665.042166, "createdAt": "2015-07-16T07:05:47.025000", "endpointUrl": "https://api.onedrive.com/", "apiName": "OneDrive"}, {"responseTime": 1392.765411, "createdAt": "2015-07-16T07:10:41.802000", "endpointUrl": "https://api.onedrive.com/", "apiName": "OneDrive"}, {"responseTime": 1167.883752, "createdAt": "2015-07-16T07:18:04.123000", "endpointUrl": "https://api.onedrive.com/", "apiName": "OneDrive"}, {"responseTime": 1024.485897, "createdAt": "2015-07-16T07:21:13.630000", "endpointUrl": "https://api.onedrive.com/", "apiName": "OneDrive"}, {"responseTime": 1149.309466, "createdAt": "2015-07-16T07:24:09.378000", "endpointUrl": "https://api.onedrive.com/", "apiName": "OneDrive"}, {"responseTime": 1286.488175, "createdAt": "2015-07-16T07:27:01.232000", "endpointUrl": "https://api.onedrive.com/", "apiName": "OneDrive"}, {"responseTime": 1219.558385, "createdAt": "2015-07-16T07:29:15.572000", "endpointUrl": "https://api.onedrive.com/", "apiName": "OneDrive"}, {"responseTime": 1398.996862, "createdAt": "2015-07-16T11:33:54.224000", "endpointUrl": "https://api.onedrive.com/", "apiName": "OneDrive"}, {"responseTime": 1343.388902, "createdAt": "2015-07-16T11:40:37.145000", "endpointUrl": "https://api.onedrive.com/", "apiName": "OneDrive"}, {"responseTime": 1497.815506, "createdAt": "2015-07-16T11:49:16.167000", "endpointUrl": "https://api.onedrive.com/", "apiName": "OneDrive"}, {"responseTime": 1401.116671, "createdAt": "2015-07-16T11:51:56.606000", "endpointUrl": "https://api.onedrive.com/", "apiName": "OneDrive"}, {"responseTime": 1410.509832, "createdAt": "2015-07-16T11:55:20.897000", "endpointUrl": "https://api.onedrive.com/", "apiName": "OneDrive"}, {"responseTime": 1404.071468, "createdAt": "2015-07-16T12:00:42.355000", "endpointUrl": "https://api.onedrive.com/", "apiName": "OneDrive"}, {"responseTime": 1425.367423, "createdAt": "2015-07-16T12:04:00.247000", "endpointUrl": "https://api.onedrive.com/", "apiName": "OneDrive"}, {"responseTime": 1476.664566, "createdAt": "2015-07-16T12:06:17.527000", "endpointUrl": "https://api.onedrive.com/", "apiName": "OneDrive"}, {"responseTime": 1555.313315, "createdAt": "2015-07-16T12:09:39.672000", "endpointUrl": "https://api.onedrive.com/", "apiName": "OneDrive"}, {"responseTime": 1523.017492, "createdAt": "2015-07-16T12:14:08.988000", "endpointUrl": "https://api.onedrive.com/", "apiName": "OneDrive"}, {"responseTime": 5589.179762, "createdAt": "2015-07-16T12:16:46.261000", "endpointUrl": "https://api.onedrive.com/", "apiName": "OneDrive"}, {"responseTime": 2405.990187, "createdAt": "2015-07-16T12:22:13.779000", "endpointUrl": "https://api.onedrive.com/", "apiName": "OneDrive"}, {"responseTime": 1451.64164, "createdAt": "2015-07-16T12:27:11.663000", "endpointUrl": "https://api.onedrive.com/", "apiName": "OneDrive"}, {"responseTime": 1791.698998, "createdAt": "2015-07-16T12:29:23.972000", "endpointUrl": "https://api.onedrive.com/", "apiName": "OneDrive"}, {"responseTime": 1170.058285, "createdAt": "2015-07-16T23:45:56.611000", "endpointUrl": "https://api.onedrive.com/", "apiName": "OneDrive"}, {"responseTime": 898.94303, "createdAt": "2015-07-16T23:48:28.294000", "endpointUrl": "https://api.onedrive.com/", "apiName": "OneDrive"}, {"responseTime": 1220.689462, "createdAt": "2015-07-16T23:51:58.277000", "endpointUrl": "https://api.onedrive.com/", "apiName": "OneDrive"}, {"responseTime": 974.058986, "createdAt": "2015-07-16T23:54:08.059000", "endpointUrl": "https://api.onedrive.com/", "apiName": "OneDrive"}, {"responseTime": 1178.471638, "createdAt": "2015-07-16T23:58:13.366000", "endpointUrl": "https://api.onedrive.com/", "apiName": "OneDrive"}, {"responseTime": 1173.009627, "createdAt": "2015-07-17T00:06:29.358000", "endpointUrl": "https://api.onedrive.com/", "apiName": "OneDrive"}, {"responseTime": 1276.569948, "createdAt": "2015-07-17T00:13:13.886000", "endpointUrl": "https://api.onedrive.com/", "apiName": "OneDrive"}, {"responseTime": 1151.661327, "createdAt": "2015-07-17T00:16:19.419000", "endpointUrl": "https://api.onedrive.com/", "apiName": "OneDrive"}, {"responseTime": 1224.129241, "createdAt": "2015-07-17T00:23:29.685000", "endpointUrl": "https://api.onedrive.com/", "apiName": "OneDrive"}, {"responseTime": 1138.239273, "createdAt": "2015-07-17T00:27:33.070000", "endpointUrl": "https://api.onedrive.com/", "apiName": "OneDrive"}, {"responseTime": 1129.819815, "createdAt": "2015-07-17T00:30:12.182000", "endpointUrl": "https://api.onedrive.com/", "apiName": "OneDrive"}, {"responseTime": 1488.621093, "createdAt": "2015-07-17T06:33:09.326000", "endpointUrl": "https://api.onedrive.com/", "apiName": "OneDrive"}, {"responseTime": 970.923031, "createdAt": "2015-07-17T06:35:25.654000", "endpointUrl": "https://api.onedrive.com/", "apiName": "OneDrive"}, {"responseTime": 1026.951992, "createdAt": "2015-07-17T06:38:29.153000", "endpointUrl": "https://api.onedrive.com/", "apiName": "OneDrive"}, {"responseTime": 1122.719564, "createdAt": "2015-07-17T06:40:48.077000", "endpointUrl": "https://api.onedrive.com/", "apiName": "OneDrive"}, {"responseTime": 1135.080165, "createdAt": "2015-07-17T06:43:34.584000", "endpointUrl": "https://api.onedrive.com/", "apiName": "OneDrive"}, {"responseTime": 848.598501, "createdAt": "2015-07-17T06:46:16.563000", "endpointUrl": "https://api.onedrive.com/", "apiName": "OneDrive"}, {"responseTime": 1326.047527, "createdAt": "2015-07-17T06:49:37.636000", "endpointUrl": "https://api.onedrive.com/", "apiName": "OneDrive"}, {"responseTime": 1099.401661, "createdAt": "2015-07-17T06:56:19.906000", "endpointUrl": "https://api.onedrive.com/", "apiName": "OneDrive"}, {"responseTime": 1148.560154, "createdAt": "2015-07-17T07:01:03.570000", "endpointUrl": "https://api.onedrive.com/", "apiName": "OneDrive"}, {"responseTime": 1191.998731, "createdAt": "2015-07-17T07:06:34.554000", "endpointUrl": "https://api.onedrive.com/", "apiName": "OneDrive"}, {"responseTime": 1044.757927, "createdAt": "2015-07-17T07:09:16.948000", "endpointUrl": "https://api.onedrive.com/", "apiName": "OneDrive"}, {"responseTime": 1024.046074, "createdAt": "2015-07-17T07:13:10.341000", "endpointUrl": "https://api.onedrive.com/", "apiName": "OneDrive"}, {"responseTime": 1492.80234, "createdAt": "2015-07-17T07:15:52.395000", "endpointUrl": "https://api.onedrive.com/", "apiName": "OneDrive"}, {"responseTime": 2575.985662, "createdAt": "2015-07-17T07:27:38.692000", "endpointUrl": "https://api.onedrive.com/", "apiName": "OneDrive"}, {"responseTime": 1122.056545, "createdAt": "2015-07-17T07:31:01.961000", "endpointUrl": "https://api.onedrive.com/", "apiName": "OneDrive"}, {"responseTime": 1483.236841, "createdAt": "2015-07-17T11:35:24.507000", "endpointUrl": "https://api.onedrive.com/", "apiName": "OneDrive"}, {"responseTime": 1381.894353, "createdAt": "2015-07-17T11:37:43.886000", "endpointUrl": "https://api.onedrive.com/", "apiName": "OneDrive"}, {"responseTime": 1389.558556, "createdAt": "2015-07-17T11:40:59.311000", "endpointUrl": "https://api.onedrive.com/", "apiName": "OneDrive"}, {"responseTime": 1485.005098, "createdAt": "2015-07-17T11:45:19.886000", "endpointUrl": "https://api.onedrive.com/", "apiName": "OneDrive"}, {"responseTime": 1217.44406, "createdAt": "2015-07-17T11:50:27.414000", "endpointUrl": "https://api.onedrive.com/", "apiName": "OneDrive"}, {"responseTime": 1462.963298, "createdAt": "2015-07-17T11:54:55.884000", "endpointUrl": "https://api.onedrive.com/", "apiName": "OneDrive"}, {"responseTime": 1326.688735, "createdAt": "2015-07-17T11:57:00.158000", "endpointUrl": "https://api.onedrive.com/", "apiName": "OneDrive"}, {"responseTime": 1315.136291, "createdAt": "2015-07-17T11:59:19.294000", "endpointUrl": "https://api.onedrive.com/", "apiName": "OneDrive"}, {"responseTime": 1061.136889, "createdAt": "2015-07-17T12:03:05.331000", "endpointUrl": "https://api.onedrive.com/", "apiName": "OneDrive"}, {"responseTime": 1013.873954, "createdAt": "2015-07-17T12:05:58.444000", "endpointUrl": "https://api.onedrive.com/", "apiName": "OneDrive"}, {"responseTime": 1622.505541, "createdAt": "2015-07-17T12:09:42.667000", "endpointUrl": "https://api.onedrive.com/", "apiName": "OneDrive"}, {"responseTime": 2562.208487, "createdAt": "2015-07-17T12:13:06.914000", "endpointUrl": "https://api.onedrive.com/", "apiName": "OneDrive"}, {"responseTime": 1155.658784, "createdAt": "2015-07-17T12:16:45.864000", "endpointUrl": "https://api.onedrive.com/", "apiName": "OneDrive"}, {"responseTime": 1647.37273, "createdAt": "2015-07-17T12:25:42.618000", "endpointUrl": "https://api.onedrive.com/", "apiName": "OneDrive"}, {"responseTime": 2237.841203, "createdAt": "2015-07-17T12:29:03.411000", "endpointUrl": "https://api.onedrive.com/", "apiName": "OneDrive"}, {"responseTime": 1438.509263, "createdAt": "2015-07-17T23:31:47.061000", "endpointUrl": "https://api.onedrive.com/", "apiName": "OneDrive"}, {"responseTime": 1129.259948, "createdAt": "2015-07-17T23:35:04.047000", "endpointUrl": "https://api.onedrive.com/", "apiName": "OneDrive"}, {"responseTime": 958.062233, "createdAt": "2015-07-17T23:37:38.205000", "endpointUrl": "https://api.onedrive.com/", "apiName": "OneDrive"}, {"responseTime": 1160.813934, "createdAt": "2015-07-17T23:41:16.853000", "endpointUrl": "https://api.onedrive.com/", "apiName": "OneDrive"}, {"responseTime": 1211.264481, "createdAt": "2015-07-17T23:44:19.113000", "endpointUrl": "https://api.onedrive.com/", "apiName": "OneDrive"}, {"responseTime": 1013.010058, "createdAt": "2015-07-17T23:46:20.761000", "endpointUrl": "https://api.onedrive.com/", "apiName": "OneDrive"}, {"responseTime": 1061.622801, "createdAt": "2015-07-17T23:49:53.987000", "endpointUrl": "https://api.onedrive.com/", "apiName": "OneDrive"}, {"responseTime": 927.539205, "createdAt": "2015-07-17T23:52:31.895000", "endpointUrl": "https://api.onedrive.com/", "apiName": "OneDrive"}, {"responseTime": 1111.949101, "createdAt": "2015-07-17T23:56:21.692000", "endpointUrl": "https://api.onedrive.com/", "apiName": "OneDrive"}, {"responseTime": 1099.075871, "createdAt": "2015-07-17T23:58:36.823000", "endpointUrl": "https://api.onedrive.com/", "apiName": "OneDrive"}, {"responseTime": 1196.890667, "createdAt": "2015-07-18T00:03:35.778000", "endpointUrl": "https://api.onedrive.com/", "apiName": "OneDrive"}, {"responseTime": 1289.693101, "createdAt": "2015-07-18T00:10:07.990000", "endpointUrl": "https://api.onedrive.com/", "apiName": "OneDrive"}, {"responseTime": 1024.502537, "createdAt": "2015-07-18T00:13:49.793000", "endpointUrl": "https://api.onedrive.com/", "apiName": "OneDrive"}, {"responseTime": 1086.954858, "createdAt": "2015-07-18T00:16:07.172000", "endpointUrl": "https://api.onedrive.com/", "apiName": "OneDrive"}, {"responseTime": 1480.803618, "createdAt": "2015-07-18T00:18:14.207000", "endpointUrl": "https://api.onedrive.com/", "apiName": "OneDrive"}, {"responseTime": 1240.761255, "createdAt": "2015-07-18T00:21:06.994000", "endpointUrl": "https://api.onedrive.com/", "apiName": "OneDrive"}, {"responseTime": 1146.368705, "createdAt": "2015-07-18T00:23:22.928000", "endpointUrl": "https://api.onedrive.com/", "apiName": "OneDrive"}, {"responseTime": 1092.980833, "createdAt": "2015-07-18T00:27:34.085000", "endpointUrl": "https://api.onedrive.com/", "apiName": "OneDrive"}, {"responseTime": 948.50524, "createdAt": "2015-07-18T00:29:35.181000", "endpointUrl": "https://api.onedrive.com/", "apiName": "OneDrive"}, {"responseTime": 1202.439083, "createdAt": "2015-07-18T06:31:30.703000", "endpointUrl": "https://api.onedrive.com/", "apiName": "OneDrive"}, {"responseTime": 1470.63048, "createdAt": "2015-07-18T06:35:50.560000", "endpointUrl": "https://api.onedrive.com/", "apiName": "OneDrive"}, {"responseTime": 1347.32463, "createdAt": "2015-07-18T06:38:22.680000", "endpointUrl": "https://api.onedrive.com/", "apiName": "OneDrive"}, {"responseTime": 1389.604269, "createdAt": "2015-07-18T06:42:28.736000", "endpointUrl": "https://api.onedrive.com/", "apiName": "OneDrive"}, {"responseTime": 1341.754465, "createdAt": "2015-07-18T06:46:50.789000", "endpointUrl": "https://api.onedrive.com/", "apiName": "OneDrive"}, {"responseTime": 1593.203241, "createdAt": "2015-07-18T06:50:06.222000", "endpointUrl": "https://api.onedrive.com/", "apiName": "OneDrive"}, {"responseTime": 1181.450221, "createdAt": "2015-07-18T06:53:08.269000", "endpointUrl": "https://api.onedrive.com/", "apiName": "OneDrive"}, {"responseTime": 1214.784855, "createdAt": "2015-07-18T06:57:27.190000", "endpointUrl": "https://api.onedrive.com/", "apiName": "OneDrive"}, {"responseTime": 1101.716658, "createdAt": "2015-07-18T06:59:36.396000", "endpointUrl": "https://api.onedrive.com/", "apiName": "OneDrive"}, {"responseTime": 1422.654301, "createdAt": "2015-07-18T07:03:13.206000", "endpointUrl": "https://api.onedrive.com/", "apiName": "OneDrive"}, {"responseTime": 1217.935301, "createdAt": "2015-07-18T07:05:17.038000", "endpointUrl": "https://api.onedrive.com/", "apiName": "OneDrive"}, {"responseTime": 1082.720383, "createdAt": "2015-07-18T07:07:32.153000", "endpointUrl": "https://api.onedrive.com/", "apiName": "OneDrive"}, {"responseTime": 1271.308764, "createdAt": "2015-07-18T07:10:44.842000", "endpointUrl": "https://api.onedrive.com/", "apiName": "OneDrive"}, {"responseTime": 1257.600159, "createdAt": "2015-07-18T07:13:52.527000", "endpointUrl": "https://api.onedrive.com/", "apiName": "OneDrive"}, {"responseTime": 1306.388136, "createdAt": "2015-07-18T07:16:34.027000", "endpointUrl": "https://api.onedrive.com/", "apiName": "OneDrive"}, {"responseTime": 1167.771791, "createdAt": "2015-07-18T07:20:19.302000", "endpointUrl": "https://api.onedrive.com/", "apiName": "OneDrive"}, {"responseTime": 2036.528815, "createdAt": "2015-07-18T07:22:45.583000", "endpointUrl": "https://api.onedrive.com/", "apiName": "OneDrive"}, {"responseTime": 1302.860261, "createdAt": "2015-07-18T07:26:40.344000", "endpointUrl": "https://api.onedrive.com/", "apiName": "OneDrive"}, {"responseTime": 1244.825299, "createdAt": "2015-07-18T07:30:07.939000", "endpointUrl": "https://api.onedrive.com/", "apiName": "OneDrive"}, {"responseTime": 1464.731189, "createdAt": "2015-07-18T11:32:15.211000", "endpointUrl": "https://api.onedrive.com/", "apiName": "OneDrive"}, {"responseTime": 1573.87016, "createdAt": "2015-07-18T11:36:43.800000", "endpointUrl": "https://api.onedrive.com/", "apiName": "OneDrive"}, {"responseTime": 1925.611238, "createdAt": "2015-07-18T11:39:10.208000", "endpointUrl": "https://api.onedrive.com/", "apiName": "OneDrive"}, {"responseTime": 1225.464041, "createdAt": "2015-07-18T11:41:13.286000", "endpointUrl": "https://api.onedrive.com/", "apiName": "OneDrive"}, {"responseTime": 1283.927066, "createdAt": "2015-07-18T11:44:24.432000", "endpointUrl": "https://api.onedrive.com/", "apiName": "OneDrive"}, {"responseTime": 1126.463283, "createdAt": "2015-07-18T11:46:34.290000", "endpointUrl": "https://api.onedrive.com/", "apiName": "OneDrive"}, {"responseTime": 1472.629454, "createdAt": "2015-07-18T11:50:41.857000", "endpointUrl": "https://api.onedrive.com/", "apiName": "OneDrive"}, {"responseTime": 1325.614633, "createdAt": "2015-07-18T11:55:19.395000", "endpointUrl": "https://api.onedrive.com/", "apiName": "OneDrive"}, {"responseTime": 1215.655493, "createdAt": "2015-07-18T11:58:12.079000", "endpointUrl": "https://api.onedrive.com/", "apiName": "OneDrive"}, {"responseTime": 1095.084982, "createdAt": "2015-07-18T12:03:52.610000", "endpointUrl": "https://api.onedrive.com/", "apiName": "OneDrive"}, {"responseTime": 1765.913046, "createdAt": "2015-07-18T12:06:43.058000", "endpointUrl": "https://api.onedrive.com/", "apiName": "OneDrive"}, {"responseTime": 1547.075555, "createdAt": "2015-07-18T12:09:01.712000", "endpointUrl": "https://api.onedrive.com/", "apiName": "OneDrive"}, {"responseTime": 1492.433277, "createdAt": "2015-07-18T12:13:33.651000", "endpointUrl": "https://api.onedrive.com/", "apiName": "OneDrive"}, {"responseTime": 1550.908524, "createdAt": "2015-07-18T12:16:47.770000", "endpointUrl": "https://api.onedrive.com/", "apiName": "OneDrive"}, {"responseTime": 1436.266609, "createdAt": "2015-07-18T12:21:35.460000", "endpointUrl": "https://api.onedrive.com/", "apiName": "OneDrive"}, {"responseTime": 1502.652135, "createdAt": "2015-07-18T12:24:52.735000", "endpointUrl": "https://api.onedrive.com/", "apiName": "OneDrive"}, {"responseTime": 1322.295953, "createdAt": "2015-07-18T12:26:55.803000", "endpointUrl": "https://api.onedrive.com/", "apiName": "OneDrive"}, {"responseTime": 1747.387328, "createdAt": "2015-07-18T12:31:09.505000", "endpointUrl": "https://api.onedrive.com/", "apiName": "OneDrive"}]