[{"responseTime": 116.076594, "createdAt": "2015-09-11T00:00:45.547000", "endpointUrl": "http://api.taobao.com", "apiName": "Taobao (cn)"}, {"responseTime": 83.535902, "createdAt": "2015-09-11T00:03:01.237000", "endpointUrl": "http://open.taobao.com", "apiName": "Taobao (cn)"}, {"responseTime": 85.067925, "createdAt": "2015-09-11T00:05:28.503000", "endpointUrl": "http://open.taobao.com", "apiName": "Taobao (cn)"}, {"responseTime": 127.104633, "createdAt": "2015-09-11T00:07:11.741000", "endpointUrl": "http://api.taobao.com", "apiName": "Taobao (cn)"}, {"responseTime": 137.271339, "createdAt": "2015-09-11T00:11:02.013000", "endpointUrl": "http://api.taobao.com", "apiName": "Taobao (cn)"}, {"responseTime": 95.940773, "createdAt": "2015-09-11T00:11:54.910000", "endpointUrl": "http://open.taobao.com", "apiName": "Taobao (cn)"}, {"responseTime": 140.37135, "createdAt": "2015-09-11T00:13:06.325000", "endpointUrl": "http://api.taobao.com", "apiName": "Taobao (cn)"}, {"responseTime": 72.424881, "createdAt": "2015-09-11T00:16:33.297000", "endpointUrl": "http://api.taobao.com", "apiName": "Taobao (cn)"}, {"responseTime": 92.721484, "createdAt": "2015-09-11T00:17:48.293000", "endpointUrl": "http://open.taobao.com", "apiName": "Taobao (cn)"}, {"responseTime": 93.584242, "createdAt": "2015-09-11T00:20:08.730000", "endpointUrl": "http://open.taobao.com", "apiName": "Taobao (cn)"}, {"responseTime": 175.004348, "createdAt": "2015-09-11T00:22:32.074000", "endpointUrl": "http://api.taobao.com", "apiName": "Taobao (cn)"}, {"responseTime": 98.608185, "createdAt": "2015-09-11T00:24:11.274000", "endpointUrl": "http://open.taobao.com", "apiName": "Taobao (cn)"}, {"responseTime": 85.719334, "createdAt": "2015-09-11T00:26:32.473000", "endpointUrl": "http://api.taobao.com", "apiName": "Taobao (cn)"}, {"responseTime": 79.55213, "createdAt": "2015-09-11T00:28:00.229000", "endpointUrl": "http://open.taobao.com", "apiName": "Taobao (cn)"}, {"responseTime": 74.740447, "createdAt": "2015-09-11T00:28:42.398000", "endpointUrl": "http://api.taobao.com", "apiName": "Taobao (cn)"}, {"responseTime": 188.074233, "createdAt": "2015-09-11T06:31:35.538000", "endpointUrl": "http://api.taobao.com", "apiName": "Taobao (cn)"}, {"responseTime": 103.694293, "createdAt": "2015-09-11T06:31:35.739000", "endpointUrl": "http://open.taobao.com", "apiName": "Taobao (cn)"}, {"responseTime": 87.528934, "createdAt": "2015-09-11T06:35:03.862000", "endpointUrl": "http://api.taobao.com", "apiName": "Taobao (cn)"}, {"responseTime": 91.09123, "createdAt": "2015-09-11T06:35:26.070000", "endpointUrl": "http://open.taobao.com", "apiName": "Taobao (cn)"}, {"responseTime": 79.128406, "createdAt": "2015-09-11T06:37:40.279000", "endpointUrl": "http://open.taobao.com", "apiName": "Taobao (cn)"}, {"responseTime": 173.274442, "createdAt": "2015-09-11T06:39:57.837000", "endpointUrl": "http://api.taobao.com", "apiName": "Taobao (cn)"}, {"responseTime": 85.768107, "createdAt": "2015-09-11T06:40:58.527000", "endpointUrl": "http://open.taobao.com", "apiName": "Taobao (cn)"}, {"responseTime": 87.940403, "createdAt": "2015-09-11T06:43:04.945000", "endpointUrl": "http://open.taobao.com", "apiName": "Taobao (cn)"}, {"responseTime": 200.274895, "createdAt": "2015-09-11T06:47:16.674000", "endpointUrl": "http://api.taobao.com", "apiName": "Taobao (cn)"}, {"responseTime": 82.513802, "createdAt": "2015-09-11T06:48:27.812000", "endpointUrl": "http://open.taobao.com", "apiName": "Taobao (cn)"}, {"responseTime": 68.956747, "createdAt": "2015-09-11T06:51:33.106000", "endpointUrl": "http://api.taobao.com", "apiName": "Taobao (cn)"}, {"responseTime": 93.567008, "createdAt": "2015-09-11T06:51:34.722000", "endpointUrl": "http://open.taobao.com", "apiName": "Taobao (cn)"}, {"responseTime": 111.329576, "createdAt": "2015-09-11T06:53:46.796000", "endpointUrl": "http://open.taobao.com", "apiName": "Taobao (cn)"}, {"responseTime": 80.786351, "createdAt": "2015-09-11T06:57:01.660000", "endpointUrl": "http://open.taobao.com", "apiName": "Taobao (cn)"}, {"responseTime": 203.163757, "createdAt": "2015-09-11T07:00:09.048000", "endpointUrl": "http://api.taobao.com", "apiName": "Taobao (cn)"}, {"responseTime": 88.408396, "createdAt": "2015-09-11T07:00:34.217000", "endpointUrl": "http://open.taobao.com", "apiName": "Taobao (cn)"}, {"responseTime": 78.219053, "createdAt": "2015-09-11T07:03:52.600000", "endpointUrl": "http://api.taobao.com", "apiName": "Taobao (cn)"}, {"responseTime": 132.629268, "createdAt": "2015-09-11T07:07:05.576000", "endpointUrl": "http://api.taobao.com", "apiName": "Taobao (cn)"}, {"responseTime": 109.128722, "createdAt": "2015-09-11T07:08:18.644000", "endpointUrl": "http://open.taobao.com", "apiName": "Taobao (cn)"}, {"responseTime": 85.241081, "createdAt": "2015-09-11T07:09:06.067000", "endpointUrl": "http://api.taobao.com", "apiName": "Taobao (cn)"}, {"responseTime": 97.007256, "createdAt": "2015-09-11T07:10:52.175000", "endpointUrl": "http://open.taobao.com", "apiName": "Taobao (cn)"}, {"responseTime": 91.113459, "createdAt": "2015-09-11T07:13:28.481000", "endpointUrl": "http://open.taobao.com", "apiName": "Taobao (cn)"}, {"responseTime": 102.39761, "createdAt": "2015-09-11T07:15:46.976000", "endpointUrl": "http://open.taobao.com", "apiName": "Taobao (cn)"}, {"responseTime": 185.319764, "createdAt": "2015-09-11T07:19:11.597000", "endpointUrl": "http://api.taobao.com", "apiName": "Taobao (cn)"}, {"responseTime": 85.134207, "createdAt": "2015-09-11T07:21:22.237000", "endpointUrl": "http://api.taobao.com", "apiName": "Taobao (cn)"}, {"responseTime": 117.661088, "createdAt": "2015-09-11T07:21:45.820000", "endpointUrl": "http://open.taobao.com", "apiName": "Taobao (cn)"}, {"responseTime": 145.059265, "createdAt": "2015-09-11T07:28:53.216000", "endpointUrl": "http://api.taobao.com", "apiName": "Taobao (cn)"}, {"responseTime": 91.342494, "createdAt": "2015-09-11T07:31:03.041000", "endpointUrl": "http://open.taobao.com", "apiName": "Taobao (cn)"}, {"responseTime": 166.725152, "createdAt": "2015-09-11T11:35:15.296000", "endpointUrl": "http://api.taobao.com", "apiName": "Taobao (cn)"}, {"responseTime": 90.241405, "createdAt": "2015-09-11T11:35:30.463000", "endpointUrl": "http://open.taobao.com", "apiName": "Taobao (cn)"}, {"responseTime": 77.734514, "createdAt": "2015-09-11T11:37:51.577000", "endpointUrl": "http://open.taobao.com", "apiName": "Taobao (cn)"}, {"responseTime": 68.764183, "createdAt": "2015-09-11T11:39:10.471000", "endpointUrl": "http://api.taobao.com", "apiName": "Taobao (cn)"}, {"responseTime": 78.411527, "createdAt": "2015-09-11T11:40:10.542000", "endpointUrl": "http://open.taobao.com", "apiName": "Taobao (cn)"}, {"responseTime": 177.429934, "createdAt": "2015-09-11T11:41:26.791000", "endpointUrl": "http://api.taobao.com", "apiName": "Taobao (cn)"}, {"responseTime": 76.492472, "createdAt": "2015-09-11T11:43:15.370000", "endpointUrl": "http://open.taobao.com", "apiName": "Taobao (cn)"}, {"responseTime": 85.402039, "createdAt": "2015-09-11T11:44:18.936000", "endpointUrl": "http://api.taobao.com", "apiName": "Taobao (cn)"}, {"responseTime": 82.090098, "createdAt": "2015-09-11T11:46:33.503000", "endpointUrl": "http://open.taobao.com", "apiName": "Taobao (cn)"}, {"responseTime": 131.289841, "createdAt": "2015-09-11T11:47:25.989000", "endpointUrl": "http://api.taobao.com", "apiName": "Taobao (cn)"}, {"responseTime": 88.346899, "createdAt": "2015-09-11T11:48:39.804000", "endpointUrl": "http://open.taobao.com", "apiName": "Taobao (cn)"}, {"responseTime": 73.997086, "createdAt": "2015-09-11T11:50:03.158000", "endpointUrl": "http://api.taobao.com", "apiName": "Taobao (cn)"}, {"responseTime": 100.02206, "createdAt": "2015-09-11T11:52:10.436000", "endpointUrl": "http://open.taobao.com", "apiName": "Taobao (cn)"}, {"responseTime": 396.809078, "createdAt": "2015-09-11T11:55:10.066000", "endpointUrl": "http://open.taobao.com", "apiName": "Taobao (cn)"}, {"responseTime": 168.175442, "createdAt": "2015-09-11T11:57:16.564000", "endpointUrl": "http://api.taobao.com", "apiName": "Taobao (cn)"}, {"responseTime": 86.859528, "createdAt": "2015-09-11T11:57:25.469000", "endpointUrl": "http://open.taobao.com", "apiName": "Taobao (cn)"}, {"responseTime": 80.222449, "createdAt": "2015-09-11T11:59:27.376000", "endpointUrl": "http://open.taobao.com", "apiName": "Taobao (cn)"}, {"responseTime": 131.069242, "createdAt": "2015-09-11T12:07:03.582000", "endpointUrl": "http://api.taobao.com", "apiName": "Taobao (cn)"}, {"responseTime": 80.76256, "createdAt": "2015-09-11T12:10:12.127000", "endpointUrl": "http://open.taobao.com", "apiName": "Taobao (cn)"}, {"responseTime": 137.245282, "createdAt": "2015-09-11T12:11:57.536000", "endpointUrl": "http://api.taobao.com", "apiName": "Taobao (cn)"}, {"responseTime": 96.092407, "createdAt": "2015-09-11T12:13:49.510000", "endpointUrl": "http://open.taobao.com", "apiName": "Taobao (cn)"}, {"responseTime": 133.307038, "createdAt": "2015-09-11T12:16:57.405000", "endpointUrl": "http://api.taobao.com", "apiName": "Taobao (cn)"}, {"responseTime": 81.999148, "createdAt": "2015-09-11T12:18:05.965000", "endpointUrl": "http://open.taobao.com", "apiName": "Taobao (cn)"}, {"responseTime": 75.671923, "createdAt": "2015-09-11T12:22:31.502000", "endpointUrl": "http://open.taobao.com", "apiName": "Taobao (cn)"}, {"responseTime": 189.21993, "createdAt": "2015-09-11T12:24:24.906000", "endpointUrl": "http://api.taobao.com", "apiName": "Taobao (cn)"}, {"responseTime": 182.085255, "createdAt": "2015-09-11T12:24:51.318000", "endpointUrl": "http://open.taobao.com", "apiName": "Taobao (cn)"}, {"responseTime": 95.702734, "createdAt": "2015-09-11T12:29:52.202000", "endpointUrl": "http://api.taobao.com", "apiName": "Taobao (cn)"}, {"responseTime": 98.596058, "createdAt": "2015-09-11T12:31:26.882000", "endpointUrl": "http://open.taobao.com", "apiName": "Taobao (cn)"}, {"responseTime": 140.661781, "createdAt": "2015-09-11T23:32:40.405000", "endpointUrl": "http://api.taobao.com", "apiName": "Taobao (cn)"}, {"responseTime": 130.792624, "createdAt": "2015-09-11T23:32:45.532000", "endpointUrl": "http://open.taobao.com", "apiName": "Taobao (cn)"}, {"responseTime": 89.615562, "createdAt": "2015-09-11T23:34:48.972000", "endpointUrl": "http://api.taobao.com", "apiName": "Taobao (cn)"}, {"responseTime": 88.828404, "createdAt": "2015-09-11T23:37:33.696000", "endpointUrl": "http://api.taobao.com", "apiName": "Taobao (cn)"}, {"responseTime": 77.673345, "createdAt": "2015-09-11T23:37:47.769000", "endpointUrl": "http://open.taobao.com", "apiName": "Taobao (cn)"}, {"responseTime": 155.808035, "createdAt": "2015-09-11T23:39:50.684000", "endpointUrl": "http://api.taobao.com", "apiName": "Taobao (cn)"}, {"responseTime": 81.167799, "createdAt": "2015-09-11T23:41:59.113000", "endpointUrl": "http://open.taobao.com", "apiName": "Taobao (cn)"}, {"responseTime": 232.062866, "createdAt": "2015-09-11T23:44:50.560000", "endpointUrl": "http://api.taobao.com", "apiName": "Taobao (cn)"}, {"responseTime": 101.790609, "createdAt": "2015-09-11T23:45:09.164000", "endpointUrl": "http://open.taobao.com", "apiName": "Taobao (cn)"}, {"responseTime": 84.359837, "createdAt": "2015-09-11T23:48:02.587000", "endpointUrl": "http://open.taobao.com", "apiName": "Taobao (cn)"}, {"responseTime": 106.155536, "createdAt": "2015-09-11T23:48:34.171000", "endpointUrl": "http://api.taobao.com", "apiName": "Taobao (cn)"}, {"responseTime": 84.009025, "createdAt": "2015-09-11T23:52:15.679000", "endpointUrl": "http://open.taobao.com", "apiName": "Taobao (cn)"}, {"responseTime": 115.360482, "createdAt": "2015-09-11T23:52:35.776000", "endpointUrl": "http://api.taobao.com", "apiName": "Taobao (cn)"}, {"responseTime": 70.17413, "createdAt": "2015-09-11T23:56:56.195000", "endpointUrl": "http://api.taobao.com", "apiName": "Taobao (cn)"}, {"responseTime": 86.679149, "createdAt": "2015-09-11T23:58:58.316000", "endpointUrl": "http://api.taobao.com", "apiName": "Taobao (cn)"}, {"responseTime": 106.901517, "createdAt": "2015-09-11T23:59:40.180000", "endpointUrl": "http://open.taobao.com", "apiName": "Taobao (cn)"}, {"responseTime": 93.454674, "createdAt": "2015-09-12T00:02:38.634000", "endpointUrl": "http://open.taobao.com", "apiName": "Taobao (cn)"}, {"responseTime": 87.848336, "createdAt": "2015-09-12T00:06:00.028000", "endpointUrl": "http://open.taobao.com", "apiName": "Taobao (cn)"}, {"responseTime": 91.59224, "createdAt": "2015-09-12T00:08:06.015000", "endpointUrl": "http://open.taobao.com", "apiName": "Taobao (cn)"}, {"responseTime": 181.367583, "createdAt": "2015-09-12T00:08:27.444000", "endpointUrl": "http://api.taobao.com", "apiName": "Taobao (cn)"}, {"responseTime": 82.257242, "createdAt": "2015-09-12T00:10:14.494000", "endpointUrl": "http://open.taobao.com", "apiName": "Taobao (cn)"}, {"responseTime": 67.779947, "createdAt": "2015-09-12T00:10:43.732000", "endpointUrl": "http://api.taobao.com", "apiName": "Taobao (cn)"}, {"responseTime": 65.588771, "createdAt": "2015-09-12T00:13:09.672000", "endpointUrl": "http://api.taobao.com", "apiName": "Taobao (cn)"}, {"responseTime": 90.931956, "createdAt": "2015-09-12T00:13:12.182000", "endpointUrl": "http://open.taobao.com", "apiName": "Taobao (cn)"}, {"responseTime": 83.115895, "createdAt": "2015-09-12T00:15:57.906000", "endpointUrl": "http://open.taobao.com", "apiName": "Taobao (cn)"}, {"responseTime": 162.22468, "createdAt": "2015-09-12T00:17:38.445000", "endpointUrl": "http://api.taobao.com", "apiName": "Taobao (cn)"}, {"responseTime": 125.090531, "createdAt": "2015-09-12T00:18:04.257000", "endpointUrl": "http://open.taobao.com", "apiName": "Taobao (cn)"}, {"responseTime": 165.540135, "createdAt": "2015-09-12T00:20:30.214000", "endpointUrl": "http://api.taobao.com", "apiName": "Taobao (cn)"}, {"responseTime": 79.352395, "createdAt": "2015-09-12T00:21:36.372000", "endpointUrl": "http://open.taobao.com", "apiName": "Taobao (cn)"}, {"responseTime": 83.02399, "createdAt": "2015-09-12T00:24:19.923000", "endpointUrl": "http://open.taobao.com", "apiName": "Taobao (cn)"}, {"responseTime": 84.693366, "createdAt": "2015-09-12T00:28:21.329000", "endpointUrl": "http://open.taobao.com", "apiName": "Taobao (cn)"}, {"responseTime": 135.44634, "createdAt": "2015-09-12T00:28:30.109000", "endpointUrl": "http://api.taobao.com", "apiName": "Taobao (cn)"}, {"responseTime": 174.390882, "createdAt": "2015-09-12T06:32:39.484000", "endpointUrl": "http://api.taobao.com", "apiName": "Taobao (cn)"}, {"responseTime": 141.194997, "createdAt": "2015-09-12T06:32:42.006000", "endpointUrl": "http://open.taobao.com", "apiName": "Taobao (cn)"}, {"responseTime": 81.698722, "createdAt": "2015-09-12T06:34:52.301000", "endpointUrl": "http://open.taobao.com", "apiName": "Taobao (cn)"}, {"responseTime": 104.778635, "createdAt": "2015-09-12T06:38:57.307000", "endpointUrl": "http://open.taobao.com", "apiName": "Taobao (cn)"}, {"responseTime": 110.962925, "createdAt": "2015-09-12T06:40:59.157000", "endpointUrl": "http://api.taobao.com", "apiName": "Taobao (cn)"}, {"responseTime": 82.187241, "createdAt": "2015-09-12T06:41:38.168000", "endpointUrl": "http://open.taobao.com", "apiName": "Taobao (cn)"}, {"responseTime": 121.794141, "createdAt": "2015-09-12T06:43:45.396000", "endpointUrl": "http://api.taobao.com", "apiName": "Taobao (cn)"}, {"responseTime": 5076.275905, "createdAt": "2015-09-12T06:44:26.173000", "endpointUrl": "http://open.taobao.com", "apiName": "Taobao (cn)"}, {"responseTime": 68.602779, "createdAt": "2015-09-12T06:46:57.523000", "endpointUrl": "http://api.taobao.com", "apiName": "Taobao (cn)"}, {"responseTime": 88.662002, "createdAt": "2015-09-12T06:49:11.522000", "endpointUrl": "http://api.taobao.com", "apiName": "Taobao (cn)"}, {"responseTime": 112.437412, "createdAt": "2015-09-12T06:49:13.808000", "endpointUrl": "http://open.taobao.com", "apiName": "Taobao (cn)"}, {"responseTime": 77.719498, "createdAt": "2015-09-12T06:52:24.646000", "endpointUrl": "http://open.taobao.com", "apiName": "Taobao (cn)"}, {"responseTime": 77.150213, "createdAt": "2015-09-12T06:54:41.231000", "endpointUrl": "http://open.taobao.com", "apiName": "Taobao (cn)"}, {"responseTime": 169.021253, "createdAt": "2015-09-12T06:55:25.728000", "endpointUrl": "http://api.taobao.com", "apiName": "Taobao (cn)"}, {"responseTime": 95.207878, "createdAt": "2015-09-12T06:57:48.230000", "endpointUrl": "http://open.taobao.com", "apiName": "Taobao (cn)"}, {"responseTime": 88.890037, "createdAt": "2015-09-12T06:59:43.754000", "endpointUrl": "http://api.taobao.com", "apiName": "Taobao (cn)"}, {"responseTime": 142.590747, "createdAt": "2015-09-12T07:02:11.629000", "endpointUrl": "http://api.taobao.com", "apiName": "Taobao (cn)"}, {"responseTime": 86.510117, "createdAt": "2015-09-12T07:04:36.716000", "endpointUrl": "http://open.taobao.com", "apiName": "Taobao (cn)"}, {"responseTime": 155.239633, "createdAt": "2015-09-12T07:06:12.638000", "endpointUrl": "http://api.taobao.com", "apiName": "Taobao (cn)"}, {"responseTime": 74.056857, "createdAt": "2015-09-12T07:08:33.261000", "endpointUrl": "http://open.taobao.com", "apiName": "Taobao (cn)"}, {"responseTime": 132.821846, "createdAt": "2015-09-12T07:11:28.662000", "endpointUrl": "http://api.taobao.com", "apiName": "Taobao (cn)"}, {"responseTime": 114.558986, "createdAt": "2015-09-12T07:12:31.061000", "endpointUrl": "http://open.taobao.com", "apiName": "Taobao (cn)"}, {"responseTime": 88.704083, "createdAt": "2015-09-12T07:14:41.236000", "endpointUrl": "http://api.taobao.com", "apiName": "Taobao (cn)"}, {"responseTime": 74.528338, "createdAt": "2015-09-12T07:16:38.818000", "endpointUrl": "http://open.taobao.com", "apiName": "Taobao (cn)"}, {"responseTime": 153.914675, "createdAt": "2015-09-12T07:17:05.528000", "endpointUrl": "http://api.taobao.com", "apiName": "Taobao (cn)"}, {"responseTime": 80.383011, "createdAt": "2015-09-12T07:19:00.181000", "endpointUrl": "http://open.taobao.com", "apiName": "Taobao (cn)"}, {"responseTime": 103.339528, "createdAt": "2015-09-12T07:21:16.662000", "endpointUrl": "http://api.taobao.com", "apiName": "Taobao (cn)"}, {"responseTime": 148.254282, "createdAt": "2015-09-12T07:23:27.536000", "endpointUrl": "http://api.taobao.com", "apiName": "Taobao (cn)"}, {"responseTime": 83.77453, "createdAt": "2015-09-12T07:25:40.115000", "endpointUrl": "http://open.taobao.com", "apiName": "Taobao (cn)"}, {"responseTime": 85.101131, "createdAt": "2015-09-12T07:26:01.671000", "endpointUrl": "http://api.taobao.com", "apiName": "Taobao (cn)"}, {"responseTime": 78.238134, "createdAt": "2015-09-12T07:27:57.480000", "endpointUrl": "http://open.taobao.com", "apiName": "Taobao (cn)"}, {"responseTime": 121.189383, "createdAt": "2015-09-12T07:28:12.285000", "endpointUrl": "http://api.taobao.com", "apiName": "Taobao (cn)"}, {"responseTime": 80.283437, "createdAt": "2015-09-12T07:30:42.553000", "endpointUrl": "http://open.taobao.com", "apiName": "Taobao (cn)"}, {"responseTime": 206.386379, "createdAt": "2015-09-12T11:34:05.596000", "endpointUrl": "http://api.taobao.com", "apiName": "Taobao (cn)"}, {"responseTime": 99.501429, "createdAt": "2015-09-12T11:35:13.683000", "endpointUrl": "http://open.taobao.com", "apiName": "Taobao (cn)"}, {"responseTime": 67.677607, "createdAt": "2015-09-12T11:37:45.403000", "endpointUrl": "http://api.taobao.com", "apiName": "Taobao (cn)"}, {"responseTime": 93.384493, "createdAt": "2015-09-12T11:38:23.453000", "endpointUrl": "http://open.taobao.com", "apiName": "Taobao (cn)"}, {"responseTime": 92.957963, "createdAt": "2015-09-12T11:40:07.297000", "endpointUrl": "http://api.taobao.com", "apiName": "Taobao (cn)"}, {"responseTime": 101.152937, "createdAt": "2015-09-12T11:42:47.777000", "endpointUrl": "http://open.taobao.com", "apiName": "Taobao (cn)"}, {"responseTime": 90.021939, "createdAt": "2015-09-12T11:44:01.193000", "endpointUrl": "http://api.taobao.com", "apiName": "Taobao (cn)"}, {"responseTime": 77.925007, "createdAt": "2015-09-12T11:45:48.922000", "endpointUrl": "http://open.taobao.com", "apiName": "Taobao (cn)"}, {"responseTime": 158.771055, "createdAt": "2015-09-12T11:47:29.693000", "endpointUrl": "http://api.taobao.com", "apiName": "Taobao (cn)"}, {"responseTime": 80.019466, "createdAt": "2015-09-12T11:50:01.813000", "endpointUrl": "http://open.taobao.com", "apiName": "Taobao (cn)"}, {"responseTime": 87.420603, "createdAt": "2015-09-12T11:50:44.435000", "endpointUrl": "http://api.taobao.com", "apiName": "Taobao (cn)"}, {"responseTime": 111.297237, "createdAt": "2015-09-12T11:52:32.129000", "endpointUrl": "http://open.taobao.com", "apiName": "Taobao (cn)"}, {"responseTime": 180.986189, "createdAt": "2015-09-12T11:55:48.342000", "endpointUrl": "http://api.taobao.com", "apiName": "Taobao (cn)"}, {"responseTime": 85.277084, "createdAt": "2015-09-12T11:58:25.055000", "endpointUrl": "http://api.taobao.com", "apiName": "Taobao (cn)"}, {"responseTime": 192.684026, "createdAt": "2015-09-12T12:04:02.324000", "endpointUrl": "http://api.taobao.com", "apiName": "Taobao (cn)"}, {"responseTime": 97.384058, "createdAt": "2015-09-12T12:04:04.962000", "endpointUrl": "http://open.taobao.com", "apiName": "Taobao (cn)"}, {"responseTime": 100.779147, "createdAt": "2015-09-12T12:06:06.765000", "endpointUrl": "http://open.taobao.com", "apiName": "Taobao (cn)"}, {"responseTime": 85.248165, "createdAt": "2015-09-12T12:06:47.136000", "endpointUrl": "http://api.taobao.com", "apiName": "Taobao (cn)"}, {"responseTime": 84.27428, "createdAt": "2015-09-12T12:09:09.193000", "endpointUrl": "http://open.taobao.com", "apiName": "Taobao (cn)"}, {"responseTime": 184.452105, "createdAt": "2015-09-12T12:09:33.958000", "endpointUrl": "http://api.taobao.com", "apiName": "Taobao (cn)"}, {"responseTime": 87.763958, "createdAt": "2015-09-12T12:11:58.955000", "endpointUrl": "http://api.taobao.com", "apiName": "Taobao (cn)"}, {"responseTime": 83.221084, "createdAt": "2015-09-12T12:12:17.523000", "endpointUrl": "http://open.taobao.com", "apiName": "Taobao (cn)"}, {"responseTime": 131.714655, "createdAt": "2015-09-12T12:15:42.669000", "endpointUrl": "http://api.taobao.com", "apiName": "Taobao (cn)"}, {"responseTime": 78.889331, "createdAt": "2015-09-12T12:16:08.210000", "endpointUrl": "http://open.taobao.com", "apiName": "Taobao (cn)"}, {"responseTime": 101.276828, "createdAt": "2015-09-12T12:19:20.310000", "endpointUrl": "http://open.taobao.com", "apiName": "Taobao (cn)"}, {"responseTime": 147.977616, "createdAt": "2015-09-12T12:21:08.251000", "endpointUrl": "http://api.taobao.com", "apiName": "Taobao (cn)"}, {"responseTime": 87.625449, "createdAt": "2015-09-12T12:24:19.746000", "endpointUrl": "http://api.taobao.com", "apiName": "Taobao (cn)"}, {"responseTime": 77.631192, "createdAt": "2015-09-12T12:25:04.357000", "endpointUrl": "http://open.taobao.com", "apiName": "Taobao (cn)"}, {"responseTime": 155.357479, "createdAt": "2015-09-12T12:27:38.177000", "endpointUrl": "http://api.taobao.com", "apiName": "Taobao (cn)"}, {"responseTime": 100.960919, "createdAt": "2015-09-12T12:28:22.201000", "endpointUrl": "http://open.taobao.com", "apiName": "Taobao (cn)"}, {"responseTime": 83.815086, "createdAt": "2015-09-12T12:30:34.505000", "endpointUrl": "http://api.taobao.com", "apiName": "Taobao (cn)"}, {"responseTime": 156.059602, "createdAt": "2015-09-12T23:35:40.168000", "endpointUrl": "http://api.taobao.com", "apiName": "Taobao (cn)"}, {"responseTime": 115.469918, "createdAt": "2015-09-12T23:36:25.751000", "endpointUrl": "http://open.taobao.com", "apiName": "Taobao (cn)"}, {"responseTime": 68.495019, "createdAt": "2015-09-12T23:39:20.962000", "endpointUrl": "http://api.taobao.com", "apiName": "Taobao (cn)"}, {"responseTime": 96.40729, "createdAt": "2015-09-12T23:40:05.287000", "endpointUrl": "http://open.taobao.com", "apiName": "Taobao (cn)"}, {"responseTime": 80.452847, "createdAt": "2015-09-12T23:42:50.482000", "endpointUrl": "http://open.taobao.com", "apiName": "Taobao (cn)"}, {"responseTime": 185.869079, "createdAt": "2015-09-12T23:43:59.209000", "endpointUrl": "http://api.taobao.com", "apiName": "Taobao (cn)"}, {"responseTime": 77.120695, "createdAt": "2015-09-12T23:46:57.766000", "endpointUrl": "http://api.taobao.com", "apiName": "Taobao (cn)"}, {"responseTime": 84.095301, "createdAt": "2015-09-12T23:46:58.741000", "endpointUrl": "http://open.taobao.com", "apiName": "Taobao (cn)"}, {"responseTime": 166.263092, "createdAt": "2015-09-12T23:49:29.775000", "endpointUrl": "http://api.taobao.com", "apiName": "Taobao (cn)"}, {"responseTime": 93.305171, "createdAt": "2015-09-12T23:49:32.152000", "endpointUrl": "http://open.taobao.com", "apiName": "Taobao (cn)"}, {"responseTime": 81.507683, "createdAt": "2015-09-12T23:51:48.491000", "endpointUrl": "http://open.taobao.com", "apiName": "Taobao (cn)"}, {"responseTime": 88.387626, "createdAt": "2015-09-12T23:53:33.155000", "endpointUrl": "http://api.taobao.com", "apiName": "Taobao (cn)"}, {"responseTime": 84.218649, "createdAt": "2015-09-12T23:54:52.982000", "endpointUrl": "http://open.taobao.com", "apiName": "Taobao (cn)"}, {"responseTime": 119.391602, "createdAt": "2015-09-12T23:56:17.639000", "endpointUrl": "http://api.taobao.com", "apiName": "Taobao (cn)"}, {"responseTime": 90.222862, "createdAt": "2015-09-12T23:58:13.431000", "endpointUrl": "http://open.taobao.com", "apiName": "Taobao (cn)"}, {"responseTime": 70.295116, "createdAt": "2015-09-12T23:59:20.117000", "endpointUrl": "http://api.taobao.com", "apiName": "Taobao (cn)"}, {"responseTime": 132.142049, "createdAt": "2015-09-13T00:02:40.799000", "endpointUrl": "http://api.taobao.com", "apiName": "Taobao (cn)"}, {"responseTime": 78.372929, "createdAt": "2015-09-13T00:02:44.778000", "endpointUrl": "http://open.taobao.com", "apiName": "Taobao (cn)"}, {"responseTime": 86.019357, "createdAt": "2015-09-13T00:04:52.407000", "endpointUrl": "http://api.taobao.com", "apiName": "Taobao (cn)"}, {"responseTime": 115.532306, "createdAt": "2015-09-13T00:05:47.729000", "endpointUrl": "http://open.taobao.com", "apiName": "Taobao (cn)"}, {"responseTime": 76.768212, "createdAt": "2015-09-13T00:08:07.435000", "endpointUrl": "http://open.taobao.com", "apiName": "Taobao (cn)"}, {"responseTime": 112.484667, "createdAt": "2015-09-13T00:08:14.081000", "endpointUrl": "http://api.taobao.com", "apiName": "Taobao (cn)"}, {"responseTime": 76.412666, "createdAt": "2015-09-13T00:10:20.681000", "endpointUrl": "http://open.taobao.com", "apiName": "Taobao (cn)"}, {"responseTime": 196.43619, "createdAt": "2015-09-13T00:14:17.373000", "endpointUrl": "http://api.taobao.com", "apiName": "Taobao (cn)"}, {"responseTime": 113.105448, "createdAt": "2015-09-13T00:14:25.559000", "endpointUrl": "http://open.taobao.com", "apiName": "Taobao (cn)"}, {"responseTime": 89.424218, "createdAt": "2015-09-13T00:17:20.122000", "endpointUrl": "http://api.taobao.com", "apiName": "Taobao (cn)"}, {"responseTime": 130.879863, "createdAt": "2015-09-13T00:20:21.012000", "endpointUrl": "http://api.taobao.com", "apiName": "Taobao (cn)"}, {"responseTime": 87.573211, "createdAt": "2015-09-13T00:22:52.556000", "endpointUrl": "http://open.taobao.com", "apiName": "Taobao (cn)"}, {"responseTime": 133.110366, "createdAt": "2015-09-13T00:24:28.697000", "endpointUrl": "http://api.taobao.com", "apiName": "Taobao (cn)"}, {"responseTime": 110.478623, "createdAt": "2015-09-13T00:26:51.867000", "endpointUrl": "http://open.taobao.com", "apiName": "Taobao (cn)"}, {"responseTime": 86.304362, "createdAt": "2015-09-13T00:29:09.175000", "endpointUrl": "http://open.taobao.com", "apiName": "Taobao (cn)"}, {"responseTime": 73.106428, "createdAt": "2015-09-13T00:29:59.603000", "endpointUrl": "http://api.taobao.com", "apiName": "Taobao (cn)"}, {"responseTime": 182.970824, "createdAt": "2015-09-13T06:35:45.293000", "endpointUrl": "http://api.taobao.com", "apiName": "Taobao (cn)"}, {"responseTime": 86.532161, "createdAt": "2015-09-13T06:35:45.493000", "endpointUrl": "http://open.taobao.com", "apiName": "Taobao (cn)"}, {"responseTime": 89.096925, "createdAt": "2015-09-13T06:38:05.831000", "endpointUrl": "http://api.taobao.com", "apiName": "Taobao (cn)"}, {"responseTime": 78.626169, "createdAt": "2015-09-13T06:38:07.035000", "endpointUrl": "http://open.taobao.com", "apiName": "Taobao (cn)"}, {"responseTime": 89.841649, "createdAt": "2015-09-13T06:40:07.829000", "endpointUrl": "http://api.taobao.com", "apiName": "Taobao (cn)"}, {"responseTime": 82.277216, "createdAt": "2015-09-13T06:42:10.957000", "endpointUrl": "http://open.taobao.com", "apiName": "Taobao (cn)"}, {"responseTime": 76.576061, "createdAt": "2015-09-13T06:44:23.813000", "endpointUrl": "http://open.taobao.com", "apiName": "Taobao (cn)"}, {"responseTime": 82.795829, "createdAt": "2015-09-13T06:47:17.565000", "endpointUrl": "http://open.taobao.com", "apiName": "Taobao (cn)"}, {"responseTime": 181.616447, "createdAt": "2015-09-13T06:48:15.091000", "endpointUrl": "http://api.taobao.com", "apiName": "Taobao (cn)"}, {"responseTime": 79.045028, "createdAt": "2015-09-13T06:50:36.777000", "endpointUrl": "http://open.taobao.com", "apiName": "Taobao (cn)"}, {"responseTime": 91.390213, "createdAt": "2015-09-13T06:50:38.797000", "endpointUrl": "http://api.taobao.com", "apiName": "Taobao (cn)"}, {"responseTime": 85.456258, "createdAt": "2015-09-13T06:52:59.271000", "endpointUrl": "http://api.taobao.com", "apiName": "Taobao (cn)"}, {"responseTime": 91.56186, "createdAt": "2015-09-13T06:54:30.471000", "endpointUrl": "http://open.taobao.com", "apiName": "Taobao (cn)"}, {"responseTime": 88.928707, "createdAt": "2015-09-13T06:55:07.580000", "endpointUrl": "http://api.taobao.com", "apiName": "Taobao (cn)"}, {"responseTime": 97.145127, "createdAt": "2015-09-13T06:56:39.927000", "endpointUrl": "http://open.taobao.com", "apiName": "Taobao (cn)"}, {"responseTime": 78.015028, "createdAt": "2015-09-13T06:58:54.010000", "endpointUrl": "http://open.taobao.com", "apiName": "Taobao (cn)"}, {"responseTime": 139.849487, "createdAt": "2015-09-13T06:59:33.227000", "endpointUrl": "http://api.taobao.com", "apiName": "Taobao (cn)"}, {"responseTime": 90.460224, "createdAt": "2015-09-13T07:02:47.838000", "endpointUrl": "http://api.taobao.com", "apiName": "Taobao (cn)"}, {"responseTime": 72.014105, "createdAt": "2015-09-13T07:05:01.836000", "endpointUrl": "http://api.taobao.com", "apiName": "Taobao (cn)"}, {"responseTime": 98.948284, "createdAt": "2015-09-13T07:05:45.455000", "endpointUrl": "http://open.taobao.com", "apiName": "Taobao (cn)"}, {"responseTime": 78.823838, "createdAt": "2015-09-13T07:08:29.473000", "endpointUrl": "http://open.taobao.com", "apiName": "Taobao (cn)"}, {"responseTime": 204.406208, "createdAt": "2015-09-13T07:08:55.816000", "endpointUrl": "http://api.taobao.com", "apiName": "Taobao (cn)"}, {"responseTime": 75.883295, "createdAt": "2015-09-13T07:10:45.125000", "endpointUrl": "http://open.taobao.com", "apiName": "Taobao (cn)"}, {"responseTime": 88.321906, "createdAt": "2015-09-13T07:12:11.504000", "endpointUrl": "http://api.taobao.com", "apiName": "Taobao (cn)"}, {"responseTime": 79.072911, "createdAt": "2015-09-13T07:13:00.212000", "endpointUrl": "http://open.taobao.com", "apiName": "Taobao (cn)"}, {"responseTime": 130.024465, "createdAt": "2015-09-13T07:14:58.384000", "endpointUrl": "http://api.taobao.com", "apiName": "Taobao (cn)"}, {"responseTime": 113.486282, "createdAt": "2015-09-13T07:15:20.617000", "endpointUrl": "http://open.taobao.com", "apiName": "Taobao (cn)"}, {"responseTime": 73.400453, "createdAt": "2015-09-13T07:17:28.933000", "endpointUrl": "http://api.taobao.com", "apiName": "Taobao (cn)"}, {"responseTime": 77.67728, "createdAt": "2015-09-13T07:19:02.029000", "endpointUrl": "http://open.taobao.com", "apiName": "Taobao (cn)"}, {"responseTime": 110.345068, "createdAt": "2015-09-13T07:19:48.675000", "endpointUrl": "http://api.taobao.com", "apiName": "Taobao (cn)"}, {"responseTime": 109.743966, "createdAt": "2015-09-13T07:22:09.027000", "endpointUrl": "http://open.taobao.com", "apiName": "Taobao (cn)"}, {"responseTime": 69.868546, "createdAt": "2015-09-13T07:23:02.569000", "endpointUrl": "http://api.taobao.com", "apiName": "Taobao (cn)"}, {"responseTime": 153.546395, "createdAt": "2015-09-13T07:26:14.887000", "endpointUrl": "http://api.taobao.com", "apiName": "Taobao (cn)"}, {"responseTime": 93.917143, "createdAt": "2015-09-13T07:27:38.790000", "endpointUrl": "http://open.taobao.com", "apiName": "Taobao (cn)"}, {"responseTime": 102.786548, "createdAt": "2015-09-13T07:30:13.673000", "endpointUrl": "http://open.taobao.com", "apiName": "Taobao (cn)"}, {"responseTime": 66.500373, "createdAt": "2015-09-13T07:30:50.964000", "endpointUrl": "http://api.taobao.com", "apiName": "Taobao (cn)"}, {"responseTime": 83.43737, "createdAt": "2015-09-13T11:34:24.576000", "endpointUrl": "http://open.taobao.com", "apiName": "Taobao (cn)"}, {"responseTime": 168.764187, "createdAt": "2015-09-13T11:35:05.474000", "endpointUrl": "http://api.taobao.com", "apiName": "Taobao (cn)"}, {"responseTime": 78.804535, "createdAt": "2015-09-13T11:38:15.706000", "endpointUrl": "http://open.taobao.com", "apiName": "Taobao (cn)"}, {"responseTime": 83.180365, "createdAt": "2015-09-13T11:40:34.217000", "endpointUrl": "http://open.taobao.com", "apiName": "Taobao (cn)"}, {"responseTime": 114.549909, "createdAt": "2015-09-13T11:40:48.311000", "endpointUrl": "http://api.taobao.com", "apiName": "Taobao (cn)"}, {"responseTime": 89.102659, "createdAt": "2015-09-13T11:42:50.427000", "endpointUrl": "http://api.taobao.com", "apiName": "Taobao (cn)"}, {"responseTime": 104.556502, "createdAt": "2015-09-13T11:44:53.183000", "endpointUrl": "http://api.taobao.com", "apiName": "Taobao (cn)"}, {"responseTime": 72.527464, "createdAt": "2015-09-13T11:45:20.540000", "endpointUrl": "http://open.taobao.com", "apiName": "Taobao (cn)"}, {"responseTime": 82.112156, "createdAt": "2015-09-13T11:48:20.999000", "endpointUrl": "http://open.taobao.com", "apiName": "Taobao (cn)"}, {"responseTime": 163.859314, "createdAt": "2015-09-13T11:48:21.086000", "endpointUrl": "http://api.taobao.com", "apiName": "Taobao (cn)"}, {"responseTime": 163.631939, "createdAt": "2015-09-13T11:55:21.204000", "endpointUrl": "http://api.taobao.com", "apiName": "Taobao (cn)"}, {"responseTime": 77.549083, "createdAt": "2015-09-13T11:55:47.532000", "endpointUrl": "http://open.taobao.com", "apiName": "Taobao (cn)"}, {"responseTime": 85.877687, "createdAt": "2015-09-13T11:57:36.810000", "endpointUrl": "http://api.taobao.com", "apiName": "Taobao (cn)"}, {"responseTime": 83.244531, "createdAt": "2015-09-13T12:01:06.292000", "endpointUrl": "http://open.taobao.com", "apiName": "Taobao (cn)"}, {"responseTime": 137.452895, "createdAt": "2015-09-13T12:01:15.383000", "endpointUrl": "http://api.taobao.com", "apiName": "Taobao (cn)"}, {"responseTime": 71.462206, "createdAt": "2015-09-13T12:03:47.189000", "endpointUrl": "http://api.taobao.com", "apiName": "Taobao (cn)"}, {"responseTime": 85.381668, "createdAt": "2015-09-13T12:04:08.501000", "endpointUrl": "http://open.taobao.com", "apiName": "Taobao (cn)"}, {"responseTime": 113.479786, "createdAt": "2015-09-13T12:06:55.628000", "endpointUrl": "http://api.taobao.com", "apiName": "Taobao (cn)"}, {"responseTime": 85.188343, "createdAt": "2015-09-13T12:06:57.843000", "endpointUrl": "http://open.taobao.com", "apiName": "Taobao (cn)"}, {"responseTime": 89.893559, "createdAt": "2015-09-13T12:09:31.272000", "endpointUrl": "http://open.taobao.com", "apiName": "Taobao (cn)"}, {"responseTime": 107.481172, "createdAt": "2015-09-13T12:11:49.159000", "endpointUrl": "http://api.taobao.com", "apiName": "Taobao (cn)"}, {"responseTime": 81.858292, "createdAt": "2015-09-13T12:13:17.090000", "endpointUrl": "http://open.taobao.com", "apiName": "Taobao (cn)"}, {"responseTime": 81.658081, "createdAt": "2015-09-13T12:17:58.345000", "endpointUrl": "http://open.taobao.com", "apiName": "Taobao (cn)"}, {"responseTime": 102.349474, "createdAt": "2015-09-13T12:18:44.885000", "endpointUrl": "http://api.taobao.com", "apiName": "Taobao (cn)"}, {"responseTime": 82.565542, "createdAt": "2015-09-13T12:21:04.102000", "endpointUrl": "http://open.taobao.com", "apiName": "Taobao (cn)"}, {"responseTime": 75.854499, "createdAt": "2015-09-13T12:23:10.909000", "endpointUrl": "http://open.taobao.com", "apiName": "Taobao (cn)"}, {"responseTime": 117.039173, "createdAt": "2015-09-13T12:24:25.615000", "endpointUrl": "http://api.taobao.com", "apiName": "Taobao (cn)"}, {"responseTime": 100.058647, "createdAt": "2015-09-13T12:25:53.112000", "endpointUrl": "http://open.taobao.com", "apiName": "Taobao (cn)"}, {"responseTime": 85.788033, "createdAt": "2015-09-13T12:27:28.045000", "endpointUrl": "http://api.taobao.com", "apiName": "Taobao (cn)"}, {"responseTime": 87.876483, "createdAt": "2015-09-13T12:29:15.692000", "endpointUrl": "http://open.taobao.com", "apiName": "Taobao (cn)"}, {"responseTime": 131.051992, "createdAt": "2015-09-13T12:29:54.627000", "endpointUrl": "http://api.taobao.com", "apiName": "Taobao (cn)"}, {"responseTime": 182.756896, "createdAt": "2015-09-13T23:34:45.087000", "endpointUrl": "http://api.taobao.com", "apiName": "Taobao (cn)"}, {"responseTime": 131.867628, "createdAt": "2015-09-13T23:34:48.399000", "endpointUrl": "http://open.taobao.com", "apiName": "Taobao (cn)"}, {"responseTime": 75.779979, "createdAt": "2015-09-13T23:38:47.229000", "endpointUrl": "http://open.taobao.com", "apiName": "Taobao (cn)"}, {"responseTime": 161.113344, "createdAt": "2015-09-13T23:39:53.731000", "endpointUrl": "http://api.taobao.com", "apiName": "Taobao (cn)"}, {"responseTime": 70.667728, "createdAt": "2015-09-13T23:42:21.497000", "endpointUrl": "http://api.taobao.com", "apiName": "Taobao (cn)"}, {"responseTime": 86.449512, "createdAt": "2015-09-13T23:42:25.187000", "endpointUrl": "http://open.taobao.com", "apiName": "Taobao (cn)"}, {"responseTime": 73.64891, "createdAt": "2015-09-13T23:44:54.897000", "endpointUrl": "http://open.taobao.com", "apiName": "Taobao (cn)"}, {"responseTime": 166.21556, "createdAt": "2015-09-13T23:45:37.071000", "endpointUrl": "http://api.taobao.com", "apiName": "Taobao (cn)"}, {"responseTime": 84.048464, "createdAt": "2015-09-13T23:47:08.693000", "endpointUrl": "http://open.taobao.com", "apiName": "Taobao (cn)"}, {"responseTime": 91.363651, "createdAt": "2015-09-13T23:47:40.770000", "endpointUrl": "http://api.taobao.com", "apiName": "Taobao (cn)"}, {"responseTime": 95.806631, "createdAt": "2015-09-13T23:49:26.470000", "endpointUrl": "http://open.taobao.com", "apiName": "Taobao (cn)"}, {"responseTime": 83.006519, "createdAt": "2015-09-13T23:50:40.666000", "endpointUrl": "http://api.taobao.com", "apiName": "Taobao (cn)"}, {"responseTime": 89.077515, "createdAt": "2015-09-13T23:51:58.806000", "endpointUrl": "http://open.taobao.com", "apiName": "Taobao (cn)"}, {"responseTime": 69.762574, "createdAt": "2015-09-13T23:54:02.492000", "endpointUrl": "http://api.taobao.com", "apiName": "Taobao (cn)"}, {"responseTime": 96.31326, "createdAt": "2015-09-13T23:54:33.705000", "endpointUrl": "http://open.taobao.com", "apiName": "Taobao (cn)"}, {"responseTime": 139.264759, "createdAt": "2015-09-13T23:56:53.745000", "endpointUrl": "http://api.taobao.com", "apiName": "Taobao (cn)"}, {"responseTime": 75.264212, "createdAt": "2015-09-13T23:57:15.805000", "endpointUrl": "http://open.taobao.com", "apiName": "Taobao (cn)"}, {"responseTime": 68.741902, "createdAt": "2015-09-13T23:59:20.717000", "endpointUrl": "http://api.taobao.com", "apiName": "Taobao (cn)"}, {"responseTime": 79.622781, "createdAt": "2015-09-14T00:00:10.925000", "endpointUrl": "http://open.taobao.com", "apiName": "Taobao (cn)"}, {"responseTime": 76.536259, "createdAt": "2015-09-14T00:03:02.532000", "endpointUrl": "http://open.taobao.com", "apiName": "Taobao (cn)"}, {"responseTime": 104.684551, "createdAt": "2015-09-14T00:03:35.077000", "endpointUrl": "http://api.taobao.com", "apiName": "Taobao (cn)"}, {"responseTime": 83.207342, "createdAt": "2015-09-14T00:05:51.183000", "endpointUrl": "http://open.taobao.com", "apiName": "Taobao (cn)"}, {"responseTime": 131.127143, "createdAt": "2015-09-14T00:07:30.011000", "endpointUrl": "http://api.taobao.com", "apiName": "Taobao (cn)"}, {"responseTime": 106.428358, "createdAt": "2015-09-14T00:08:01.131000", "endpointUrl": "http://open.taobao.com", "apiName": "Taobao (cn)"}, {"responseTime": 92.52491, "createdAt": "2015-09-14T00:09:48.999000", "endpointUrl": "http://api.taobao.com", "apiName": "Taobao (cn)"}, {"responseTime": 76.094972, "createdAt": "2015-09-14T00:11:25.698000", "endpointUrl": "http://open.taobao.com", "apiName": "Taobao (cn)"}, {"responseTime": 65.956543, "createdAt": "2015-09-14T00:11:59.057000", "endpointUrl": "http://api.taobao.com", "apiName": "Taobao (cn)"}, {"responseTime": 180.354388, "createdAt": "2015-09-14T00:15:46.832000", "endpointUrl": "http://api.taobao.com", "apiName": "Taobao (cn)"}, {"responseTime": 97.011711, "createdAt": "2015-09-14T00:15:55.093000", "endpointUrl": "http://open.taobao.com", "apiName": "Taobao (cn)"}, {"responseTime": 86.860115, "createdAt": "2015-09-14T00:18:53.475000", "endpointUrl": "http://open.taobao.com", "apiName": "Taobao (cn)"}, {"responseTime": 73.651424, "createdAt": "2015-09-14T00:20:25.700000", "endpointUrl": "http://api.taobao.com", "apiName": "Taobao (cn)"}, {"responseTime": 101.475029, "createdAt": "2015-09-14T00:22:39.564000", "endpointUrl": "http://api.taobao.com", "apiName": "Taobao (cn)"}, {"responseTime": 93.897642, "createdAt": "2015-09-14T00:23:06.804000", "endpointUrl": "http://open.taobao.com", "apiName": "Taobao (cn)"}, {"responseTime": 75.058141, "createdAt": "2015-09-14T00:26:01.835000", "endpointUrl": "http://open.taobao.com", "apiName": "Taobao (cn)"}, {"responseTime": 130.262874, "createdAt": "2015-09-14T00:26:17.902000", "endpointUrl": "http://api.taobao.com", "apiName": "Taobao (cn)"}, {"responseTime": 114.721168, "createdAt": "2015-09-14T00:28:31.080000", "endpointUrl": "http://api.taobao.com", "apiName": "Taobao (cn)"}, {"responseTime": 97.331135, "createdAt": "2015-09-14T00:30:41.912000", "endpointUrl": "http://open.taobao.com", "apiName": "Taobao (cn)"}, {"responseTime": 162.829288, "createdAt": "2015-09-14T06:34:42.636000", "endpointUrl": "http://api.taobao.com", "apiName": "Taobao (cn)"}, {"responseTime": 80.482648, "createdAt": "2015-09-14T06:34:43.556000", "endpointUrl": "http://open.taobao.com", "apiName": "Taobao (cn)"}, {"responseTime": 74.877547, "createdAt": "2015-09-14T06:39:27.561000", "endpointUrl": "http://api.taobao.com", "apiName": "Taobao (cn)"}, {"responseTime": 83.772742, "createdAt": "2015-09-14T06:40:15.116000", "endpointUrl": "http://open.taobao.com", "apiName": "Taobao (cn)"}, {"responseTime": 93.217087, "createdAt": "2015-09-14T06:42:46.160000", "endpointUrl": "http://open.taobao.com", "apiName": "Taobao (cn)"}, {"responseTime": 209.4768, "createdAt": "2015-09-14T06:43:03.929000", "endpointUrl": "http://api.taobao.com", "apiName": "Taobao (cn)"}, {"responseTime": 88.905523, "createdAt": "2015-09-14T06:45:21.565000", "endpointUrl": "http://api.taobao.com", "apiName": "Taobao (cn)"}, {"responseTime": 75.57171, "createdAt": "2015-09-14T06:46:02.914000", "endpointUrl": "http://open.taobao.com", "apiName": "Taobao (cn)"}, {"responseTime": 107.126555, "createdAt": "2015-09-14T06:49:20.480000", "endpointUrl": "http://api.taobao.com", "apiName": "Taobao (cn)"}, {"responseTime": 86.780247, "createdAt": "2015-09-14T06:51:57.474000", "endpointUrl": "http://api.taobao.com", "apiName": "Taobao (cn)"}, {"responseTime": 92.399418, "createdAt": "2015-09-14T06:52:03.013000", "endpointUrl": "http://open.taobao.com", "apiName": "Taobao (cn)"}, {"responseTime": 167.103422, "createdAt": "2015-09-14T06:55:07.825000", "endpointUrl": "http://api.taobao.com", "apiName": "Taobao (cn)"}, {"responseTime": 82.887675, "createdAt": "2015-09-14T06:55:21.078000", "endpointUrl": "http://open.taobao.com", "apiName": "Taobao (cn)"}, {"responseTime": 106.433995, "createdAt": "2015-09-14T06:58:36.882000", "endpointUrl": "http://api.taobao.com", "apiName": "Taobao (cn)"}, {"responseTime": 141.0817, "createdAt": "2015-09-14T06:59:34.771000", "endpointUrl": "http://open.taobao.com", "apiName": "Taobao (cn)"}, {"responseTime": 155.109328, "createdAt": "2015-09-14T07:01:33.759000", "endpointUrl": "http://api.taobao.com", "apiName": "Taobao (cn)"}, {"responseTime": 80.088962, "createdAt": "2015-09-14T07:02:59.176000", "endpointUrl": "http://open.taobao.com", "apiName": "Taobao (cn)"}, {"responseTime": 92.914435, "createdAt": "2015-09-14T07:05:38.916000", "endpointUrl": "http://open.taobao.com", "apiName": "Taobao (cn)"}, {"responseTime": 113.725147, "createdAt": "2015-09-14T07:05:50.952000", "endpointUrl": "http://api.taobao.com", "apiName": "Taobao (cn)"}, {"responseTime": 71.716428, "createdAt": "2015-09-14T07:07:52.977000", "endpointUrl": "http://api.taobao.com", "apiName": "Taobao (cn)"}, {"responseTime": 81.269407, "createdAt": "2015-09-14T07:09:40.615000", "endpointUrl": "http://open.taobao.com", "apiName": "Taobao (cn)"}, {"responseTime": 70.811426, "createdAt": "2015-09-14T07:11:55.443000", "endpointUrl": "http://api.taobao.com", "apiName": "Taobao (cn)"}, {"responseTime": 74.149226, "createdAt": "2015-09-14T07:12:47.194000", "endpointUrl": "http://open.taobao.com", "apiName": "Taobao (cn)"}, {"responseTime": 85.18645, "createdAt": "2015-09-14T07:15:00.381000", "endpointUrl": "http://open.taobao.com", "apiName": "Taobao (cn)"}, {"responseTime": 105.037163, "createdAt": "2015-09-14T07:15:15.108000", "endpointUrl": "http://api.taobao.com", "apiName": "Taobao (cn)"}, {"responseTime": 137.12866, "createdAt": "2015-09-14T07:17:23.535000", "endpointUrl": "http://api.taobao.com", "apiName": "Taobao (cn)"}, {"responseTime": 97.366333, "createdAt": "2015-09-14T07:17:44.780000", "endpointUrl": "http://open.taobao.com", "apiName": "Taobao (cn)"}, {"responseTime": 88.414407, "createdAt": "2015-09-14T07:19:49.267000", "endpointUrl": "http://api.taobao.com", "apiName": "Taobao (cn)"}, {"responseTime": 98.398454, "createdAt": "2015-09-14T07:20:08.282000", "endpointUrl": "http://open.taobao.com", "apiName": "Taobao (cn)"}, {"responseTime": 152.051177, "createdAt": "2015-09-14T07:23:36.166000", "endpointUrl": "http://api.taobao.com", "apiName": "Taobao (cn)"}, {"responseTime": 84.805872, "createdAt": "2015-09-14T07:25:40.314000", "endpointUrl": "http://open.taobao.com", "apiName": "Taobao (cn)"}, {"responseTime": 76.502557, "createdAt": "2015-09-14T07:28:25.060000", "endpointUrl": "http://open.taobao.com", "apiName": "Taobao (cn)"}, {"responseTime": 95.861824, "createdAt": "2015-09-14T07:31:03.474000", "endpointUrl": "http://api.taobao.com", "apiName": "Taobao (cn)"}, {"responseTime": 195.952893, "createdAt": "2015-09-14T11:32:25.018000", "endpointUrl": "http://api.taobao.com", "apiName": "Taobao (cn)"}, {"responseTime": 93.933895, "createdAt": "2015-09-14T11:32:25.219000", "endpointUrl": "http://open.taobao.com", "apiName": "Taobao (cn)"}, {"responseTime": 85.777219, "createdAt": "2015-09-14T11:34:37.485000", "endpointUrl": "http://open.taobao.com", "apiName": "Taobao (cn)"}, {"responseTime": 67.521945, "createdAt": "2015-09-14T11:34:38.487000", "endpointUrl": "http://api.taobao.com", "apiName": "Taobao (cn)"}, {"responseTime": 88.198098, "createdAt": "2015-09-14T11:36:59.386000", "endpointUrl": "http://api.taobao.com", "apiName": "Taobao (cn)"}, {"responseTime": 77.608081, "createdAt": "2015-09-14T11:37:50.705000", "endpointUrl": "http://open.taobao.com", "apiName": "Taobao (cn)"}, {"responseTime": 82.867517, "createdAt": "2015-09-14T11:40:22.022000", "endpointUrl": "http://open.taobao.com", "apiName": "Taobao (cn)"}, {"responseTime": 147.916361, "createdAt": "2015-09-14T11:41:05.501000", "endpointUrl": "http://api.taobao.com", "apiName": "Taobao (cn)"}, {"responseTime": 77.520011, "createdAt": "2015-09-14T11:44:47.930000", "endpointUrl": "http://open.taobao.com", "apiName": "Taobao (cn)"}, {"responseTime": 109.8442, "createdAt": "2015-09-14T11:45:10.432000", "endpointUrl": "http://api.taobao.com", "apiName": "Taobao (cn)"}, {"responseTime": 110.90935, "createdAt": "2015-09-14T11:48:25.341000", "endpointUrl": "http://api.taobao.com", "apiName": "Taobao (cn)"}, {"responseTime": 89.419633, "createdAt": "2015-09-14T11:49:44.364000", "endpointUrl": "http://open.taobao.com", "apiName": "Taobao (cn)"}, {"responseTime": 74.77362, "createdAt": "2015-09-14T11:50:53.873000", "endpointUrl": "http://api.taobao.com", "apiName": "Taobao (cn)"}, {"responseTime": 94.813157, "createdAt": "2015-09-14T11:51:59.164000", "endpointUrl": "http://open.taobao.com", "apiName": "Taobao (cn)"}, {"responseTime": 171.610661, "createdAt": "2015-09-14T11:54:05.647000", "endpointUrl": "http://api.taobao.com", "apiName": "Taobao (cn)"}, {"responseTime": 79.015209, "createdAt": "2015-09-14T11:56:06.337000", "endpointUrl": "http://open.taobao.com", "apiName": "Taobao (cn)"}, {"responseTime": 85.473257, "createdAt": "2015-09-14T11:56:47.529000", "endpointUrl": "http://api.taobao.com", "apiName": "Taobao (cn)"}, {"responseTime": 84.766669, "createdAt": "2015-09-14T12:00:13.065000", "endpointUrl": "http://open.taobao.com", "apiName": "Taobao (cn)"}, {"responseTime": 144.094774, "createdAt": "2015-09-14T12:01:39.120000", "endpointUrl": "http://api.taobao.com", "apiName": "Taobao (cn)"}, {"responseTime": 73.25659, "createdAt": "2015-09-14T12:02:35.256000", "endpointUrl": "http://open.taobao.com", "apiName": "Taobao (cn)"}, {"responseTime": 88.695327, "createdAt": "2015-09-14T12:06:29.463000", "endpointUrl": "http://api.taobao.com", "apiName": "Taobao (cn)"}, {"responseTime": 117.257997, "createdAt": "2015-09-14T12:07:28.681000", "endpointUrl": "http://open.taobao.com", "apiName": "Taobao (cn)"}, {"responseTime": 130.00077, "createdAt": "2015-09-14T12:09:44.876000", "endpointUrl": "http://api.taobao.com", "apiName": "Taobao (cn)"}, {"responseTime": 196.103364, "createdAt": "2015-09-14T12:17:04.956000", "endpointUrl": "http://api.taobao.com", "apiName": "Taobao (cn)"}, {"responseTime": 81.882259, "createdAt": "2015-09-14T12:17:08.374000", "endpointUrl": "http://open.taobao.com", "apiName": "Taobao (cn)"}, {"responseTime": 90.301156, "createdAt": "2015-09-14T12:20:52.973000", "endpointUrl": "http://api.taobao.com", "apiName": "Taobao (cn)"}, {"responseTime": 76.908644, "createdAt": "2015-09-14T12:22:11.226000", "endpointUrl": "http://open.taobao.com", "apiName": "Taobao (cn)"}, {"responseTime": 160.865535, "createdAt": "2015-09-14T12:24:02.072000", "endpointUrl": "http://api.taobao.com", "apiName": "Taobao (cn)"}, {"responseTime": 83.639278, "createdAt": "2015-09-14T12:24:49.559000", "endpointUrl": "http://open.taobao.com", "apiName": "Taobao (cn)"}, {"responseTime": 86.765363, "createdAt": "2015-09-14T12:26:12.299000", "endpointUrl": "http://api.taobao.com", "apiName": "Taobao (cn)"}, {"responseTime": 102.065842, "createdAt": "2015-09-14T12:27:40.798000", "endpointUrl": "http://open.taobao.com", "apiName": "Taobao (cn)"}, {"responseTime": 89.593835, "createdAt": "2015-09-14T12:28:30.636000", "endpointUrl": "http://api.taobao.com", "apiName": "Taobao (cn)"}, {"responseTime": 101.436641, "createdAt": "2015-09-14T12:30:35.824000", "endpointUrl": "http://open.taobao.com", "apiName": "Taobao (cn)"}, {"responseTime": 107.135728, "createdAt": "2015-09-14T23:35:27.112000", "endpointUrl": "http://open.taobao.com", "apiName": "Taobao (cn)"}, {"responseTime": 84.659113, "createdAt": "2015-09-14T23:38:17.883000", "endpointUrl": "http://open.taobao.com", "apiName": "Taobao (cn)"}, {"responseTime": 149.650412, "createdAt": "2015-09-14T23:39:04.572000", "endpointUrl": "http://api.taobao.com", "apiName": "Taobao (cn)"}, {"responseTime": 98.507033, "createdAt": "2015-09-14T23:40:45.568000", "endpointUrl": "http://open.taobao.com", "apiName": "Taobao (cn)"}, {"responseTime": 71.265788, "createdAt": "2015-09-14T23:42:17.088000", "endpointUrl": "http://api.taobao.com", "apiName": "Taobao (cn)"}, {"responseTime": 77.548971, "createdAt": "2015-09-14T23:42:57.169000", "endpointUrl": "http://open.taobao.com", "apiName": "Taobao (cn)"}, {"responseTime": 74.95866, "createdAt": "2015-09-14T23:47:12.079000", "endpointUrl": "http://open.taobao.com", "apiName": "Taobao (cn)"}, {"responseTime": 156.829058, "createdAt": "2015-09-14T23:48:41.315000", "endpointUrl": "http://api.taobao.com", "apiName": "Taobao (cn)"}, {"responseTime": 86.95602, "createdAt": "2015-09-14T23:52:11.661000", "endpointUrl": "http://open.taobao.com", "apiName": "Taobao (cn)"}, {"responseTime": 171.958552, "createdAt": "2015-09-14T23:56:59.065000", "endpointUrl": "http://api.taobao.com", "apiName": "Taobao (cn)"}, {"responseTime": 89.270453, "createdAt": "2015-09-14T23:58:01.003000", "endpointUrl": "http://open.taobao.com", "apiName": "Taobao (cn)"}, {"responseTime": 86.521281, "createdAt": "2015-09-14T23:59:31.259000", "endpointUrl": "http://api.taobao.com", "apiName": "Taobao (cn)"}, {"responseTime": 82.341489, "createdAt": "2015-09-15T00:00:10.570000", "endpointUrl": "http://open.taobao.com", "apiName": "Taobao (cn)"}, {"responseTime": 93.259522, "createdAt": "2015-09-15T00:05:05.208000", "endpointUrl": "http://api.taobao.com", "apiName": "Taobao (cn)"}, {"responseTime": 74.987191, "createdAt": "2015-09-15T00:07:02.549000", "endpointUrl": "http://open.taobao.com", "apiName": "Taobao (cn)"}, {"responseTime": 142.46521, "createdAt": "2015-09-15T00:08:33.778000", "endpointUrl": "http://api.taobao.com", "apiName": "Taobao (cn)"}, {"responseTime": 75.458461, "createdAt": "2015-09-15T00:10:37.198000", "endpointUrl": "http://open.taobao.com", "apiName": "Taobao (cn)"}, {"responseTime": 104.224419, "createdAt": "2015-09-15T00:13:03.767000", "endpointUrl": "http://api.taobao.com", "apiName": "Taobao (cn)"}, {"responseTime": 80.861273, "createdAt": "2015-09-15T00:14:10.765000", "endpointUrl": "http://open.taobao.com", "apiName": "Taobao (cn)"}, {"responseTime": 89.889915, "createdAt": "2015-09-15T00:15:54.348000", "endpointUrl": "http://api.taobao.com", "apiName": "Taobao (cn)"}, {"responseTime": 73.32263, "createdAt": "2015-09-15T00:16:13.508000", "endpointUrl": "http://open.taobao.com", "apiName": "Taobao (cn)"}, {"responseTime": 76.136919, "createdAt": "2015-09-15T00:18:35.356000", "endpointUrl": "http://open.taobao.com", "apiName": "Taobao (cn)"}, {"responseTime": 124.132259, "createdAt": "2015-09-15T00:18:55.403000", "endpointUrl": "http://api.taobao.com", "apiName": "Taobao (cn)"}, {"responseTime": 83.190937, "createdAt": "2015-09-15T00:21:03.132000", "endpointUrl": "http://open.taobao.com", "apiName": "Taobao (cn)"}, {"responseTime": 88.337671, "createdAt": "2015-09-15T00:21:32.788000", "endpointUrl": "http://api.taobao.com", "apiName": "Taobao (cn)"}, {"responseTime": 82.34285, "createdAt": "2015-09-15T00:23:37.741000", "endpointUrl": "http://open.taobao.com", "apiName": "Taobao (cn)"}, {"responseTime": 155.991972, "createdAt": "2015-09-15T00:25:14.470000", "endpointUrl": "http://api.taobao.com", "apiName": "Taobao (cn)"}, {"responseTime": 67.651878, "createdAt": "2015-09-15T00:28:25.566000", "endpointUrl": "http://api.taobao.com", "apiName": "Taobao (cn)"}, {"responseTime": 98.381881, "createdAt": "2015-09-15T00:30:29.102000", "endpointUrl": "http://open.taobao.com", "apiName": "Taobao (cn)"}, {"responseTime": 79.343821, "createdAt": "2015-09-15T06:37:24.299000", "endpointUrl": "http://open.taobao.com", "apiName": "Taobao (cn)"}, {"responseTime": 138.943889, "createdAt": "2015-09-15T06:38:23.969000", "endpointUrl": "http://api.taobao.com", "apiName": "Taobao (cn)"}, {"responseTime": 66.768815, "createdAt": "2015-09-15T06:40:41.702000", "endpointUrl": "http://api.taobao.com", "apiName": "Taobao (cn)"}, {"responseTime": 85.078792, "createdAt": "2015-09-15T06:41:05.415000", "endpointUrl": "http://open.taobao.com", "apiName": "Taobao (cn)"}, {"responseTime": 86.05821, "createdAt": "2015-09-15T06:43:17.047000", "endpointUrl": "http://api.taobao.com", "apiName": "Taobao (cn)"}, {"responseTime": 107.977697, "createdAt": "2015-09-15T06:45:01.999000", "endpointUrl": "http://open.taobao.com", "apiName": "Taobao (cn)"}, {"responseTime": 175.454227, "createdAt": "2015-09-15T06:47:40.568000", "endpointUrl": "http://api.taobao.com", "apiName": "Taobao (cn)"}, {"responseTime": 86.798022, "createdAt": "2015-09-15T06:47:42.512000", "endpointUrl": "http://open.taobao.com", "apiName": "Taobao (cn)"}, {"responseTime": 87.679308, "createdAt": "2015-09-15T06:49:50.249000", "endpointUrl": "http://api.taobao.com", "apiName": "Taobao (cn)"}, {"responseTime": 95.818425, "createdAt": "2015-09-15T06:52:50.621000", "endpointUrl": "http://api.taobao.com", "apiName": "Taobao (cn)"}, {"responseTime": 105.832129, "createdAt": "2015-09-15T06:53:24.613000", "endpointUrl": "http://open.taobao.com", "apiName": "Taobao (cn)"}, {"responseTime": 85.004703, "createdAt": "2015-09-15T06:54:56.404000", "endpointUrl": "http://api.taobao.com", "apiName": "Taobao (cn)"}, {"responseTime": 106.19048, "createdAt": "2015-09-15T06:56:30.102000", "endpointUrl": "http://open.taobao.com", "apiName": "Taobao (cn)"}, {"responseTime": 123.389888, "createdAt": "2015-09-15T06:58:52.247000", "endpointUrl": "http://api.taobao.com", "apiName": "Taobao (cn)"}, {"responseTime": 189.194616, "createdAt": "2015-09-15T07:03:58.466000", "endpointUrl": "http://api.taobao.com", "apiName": "Taobao (cn)"}, {"responseTime": 96.067067, "createdAt": "2015-09-15T07:04:05.959000", "endpointUrl": "http://open.taobao.com", "apiName": "Taobao (cn)"}, {"responseTime": 92.952606, "createdAt": "2015-09-15T07:06:25.036000", "endpointUrl": "http://api.taobao.com", "apiName": "Taobao (cn)"}, {"responseTime": 76.283059, "createdAt": "2015-09-15T07:06:28.023000", "endpointUrl": "http://open.taobao.com", "apiName": "Taobao (cn)"}, {"responseTime": 74.325295, "createdAt": "2015-09-15T07:09:47.969000", "endpointUrl": "http://api.taobao.com", "apiName": "Taobao (cn)"}, {"responseTime": 78.302553, "createdAt": "2015-09-15T07:12:43.112000", "endpointUrl": "http://open.taobao.com", "apiName": "Taobao (cn)"}, {"responseTime": 70.799342, "createdAt": "2015-09-15T07:13:34.291000", "endpointUrl": "http://api.taobao.com", "apiName": "Taobao (cn)"}, {"responseTime": 89.701022, "createdAt": "2015-09-15T07:15:27.402000", "endpointUrl": "http://open.taobao.com", "apiName": "Taobao (cn)"}, {"responseTime": 117.080411, "createdAt": "2015-09-15T07:16:14.722000", "endpointUrl": "http://api.taobao.com", "apiName": "Taobao (cn)"}, {"responseTime": 96.056713, "createdAt": "2015-09-15T07:18:08.363000", "endpointUrl": "http://open.taobao.com", "apiName": "Taobao (cn)"}, {"responseTime": 146.943701, "createdAt": "2015-09-15T07:19:08.041000", "endpointUrl": "http://api.taobao.com", "apiName": "Taobao (cn)"}, {"responseTime": 79.423497, "createdAt": "2015-09-15T07:21:23.997000", "endpointUrl": "http://api.taobao.com", "apiName": "Taobao (cn)"}, {"responseTime": 93.585201, "createdAt": "2015-09-15T07:21:25.738000", "endpointUrl": "http://open.taobao.com", "apiName": "Taobao (cn)"}, {"responseTime": 83.284787, "createdAt": "2015-09-15T07:24:26.581000", "endpointUrl": "http://open.taobao.com", "apiName": "Taobao (cn)"}, {"responseTime": 175.642014, "createdAt": "2015-09-15T07:24:51.516000", "endpointUrl": "http://api.taobao.com", "apiName": "Taobao (cn)"}, {"responseTime": 106.257116, "createdAt": "2015-09-15T07:28:39.786000", "endpointUrl": "http://api.taobao.com", "apiName": "Taobao (cn)"}, {"responseTime": 87.844729, "createdAt": "2015-09-15T07:30:39.191000", "endpointUrl": "http://open.taobao.com", "apiName": "Taobao (cn)"}, {"responseTime": 100.360919, "createdAt": "2015-09-15T11:31:47.710000", "endpointUrl": "http://open.taobao.com", "apiName": "Taobao (cn)"}, {"responseTime": 168.771982, "createdAt": "2015-09-15T11:33:27.545000", "endpointUrl": "http://api.taobao.com", "apiName": "Taobao (cn)"}, {"responseTime": 85.970782, "createdAt": "2015-09-15T11:36:12.970000", "endpointUrl": "http://api.taobao.com", "apiName": "Taobao (cn)"}, {"responseTime": 98.257362, "createdAt": "2015-09-15T11:38:13.046000", "endpointUrl": "http://open.taobao.com", "apiName": "Taobao (cn)"}, {"responseTime": 172.167068, "createdAt": "2015-09-15T11:38:46.314000", "endpointUrl": "http://api.taobao.com", "apiName": "Taobao (cn)"}, {"responseTime": 87.386672, "createdAt": "2015-09-15T11:40:55.676000", "endpointUrl": "http://api.taobao.com", "apiName": "Taobao (cn)"}, {"responseTime": 84.139433, "createdAt": "2015-09-15T11:41:06.256000", "endpointUrl": "http://open.taobao.com", "apiName": "Taobao (cn)"}, {"responseTime": 89.822933, "createdAt": "2015-09-15T11:42:56.608000", "endpointUrl": "http://api.taobao.com", "apiName": "Taobao (cn)"}, {"responseTime": 159.033514, "createdAt": "2015-09-15T11:46:02.640000", "endpointUrl": "http://api.taobao.com", "apiName": "Taobao (cn)"}, {"responseTime": 119.239991, "createdAt": "2015-09-15T11:49:01.363000", "endpointUrl": "http://open.taobao.com", "apiName": "Taobao (cn)"}, {"responseTime": 116.089761, "createdAt": "2015-09-15T11:49:01.509000", "endpointUrl": "http://api.taobao.com", "apiName": "Taobao (cn)"}, {"responseTime": 77.518847, "createdAt": "2015-09-15T11:52:55.859000", "endpointUrl": "http://open.taobao.com", "apiName": "Taobao (cn)"}, {"responseTime": 75.102391, "createdAt": "2015-09-15T11:53:58.324000", "endpointUrl": "http://api.taobao.com", "apiName": "Taobao (cn)"}, {"responseTime": 148.836509, "createdAt": "2015-09-15T11:57:48.119000", "endpointUrl": "http://api.taobao.com", "apiName": "Taobao (cn)"}, {"responseTime": 77.170066, "createdAt": "2015-09-15T11:59:45.362000", "endpointUrl": "http://open.taobao.com", "apiName": "Taobao (cn)"}, {"responseTime": 108.243932, "createdAt": "2015-09-15T12:00:05.447000", "endpointUrl": "http://api.taobao.com", "apiName": "Taobao (cn)"}, {"responseTime": 93.391442, "createdAt": "2015-09-15T12:02:31.664000", "endpointUrl": "http://api.taobao.com", "apiName": "Taobao (cn)"}, {"responseTime": 100.298983, "createdAt": "2015-09-15T12:03:03.784000", "endpointUrl": "http://open.taobao.com", "apiName": "Taobao (cn)"}, {"responseTime": 5082.675917, "createdAt": "2015-09-15T12:05:51.680000", "endpointUrl": "http://open.taobao.com", "apiName": "Taobao (cn)"}, {"responseTime": 181.046627, "createdAt": "2015-09-15T12:07:15.987000", "endpointUrl": "http://api.taobao.com", "apiName": "Taobao (cn)"}, {"responseTime": 79.666271, "createdAt": "2015-09-15T12:09:49.503000", "endpointUrl": "http://open.taobao.com", "apiName": "Taobao (cn)"}, {"responseTime": 146.501336, "createdAt": "2015-09-15T12:10:45.450000", "endpointUrl": "http://api.taobao.com", "apiName": "Taobao (cn)"}, {"responseTime": 112.925441, "createdAt": "2015-09-15T12:13:32.498000", "endpointUrl": "http://api.taobao.com", "apiName": "Taobao (cn)"}, {"responseTime": 112.249164, "createdAt": "2015-09-15T12:14:02.238000", "endpointUrl": "http://open.taobao.com", "apiName": "Taobao (cn)"}, {"responseTime": 125.50317, "createdAt": "2015-09-15T12:18:05.373000", "endpointUrl": "http://api.taobao.com", "apiName": "Taobao (cn)"}, {"responseTime": 79.242065, "createdAt": "2015-09-15T12:19:32.581000", "endpointUrl": "http://open.taobao.com", "apiName": "Taobao (cn)"}, {"responseTime": 69.486085, "createdAt": "2015-09-15T12:20:06.659000", "endpointUrl": "http://api.taobao.com", "apiName": "Taobao (cn)"}, {"responseTime": 84.784666, "createdAt": "2015-09-15T12:21:58.822000", "endpointUrl": "http://open.taobao.com", "apiName": "Taobao (cn)"}, {"responseTime": 213.375298, "createdAt": "2015-09-15T12:23:17.938000", "endpointUrl": "http://api.taobao.com", "apiName": "Taobao (cn)"}, {"responseTime": 90.410847, "createdAt": "2015-09-15T12:25:26.158000", "endpointUrl": "http://api.taobao.com", "apiName": "Taobao (cn)"}, {"responseTime": 83.520294, "createdAt": "2015-09-15T12:26:27.441000", "endpointUrl": "http://open.taobao.com", "apiName": "Taobao (cn)"}, {"responseTime": 76.813788, "createdAt": "2015-09-15T12:29:34.531000", "endpointUrl": "http://open.taobao.com", "apiName": "Taobao (cn)"}, {"responseTime": 94.061307, "createdAt": "2015-09-15T12:30:31.940000", "endpointUrl": "http://api.taobao.com", "apiName": "Taobao (cn)"}, {"responseTime": 187.833264, "createdAt": "2015-09-15T23:31:45.292000", "endpointUrl": "http://api.taobao.com", "apiName": "Taobao (cn)"}, {"responseTime": 81.690311, "createdAt": "2015-09-15T23:31:45.497000", "endpointUrl": "http://open.taobao.com", "apiName": "Taobao (cn)"}, {"responseTime": 70.700575, "createdAt": "2015-09-15T23:34:41.656000", "endpointUrl": "http://api.taobao.com", "apiName": "Taobao (cn)"}, {"responseTime": 93.489129, "createdAt": "2015-09-15T23:34:41.757000", "endpointUrl": "http://open.taobao.com", "apiName": "Taobao (cn)"}, {"responseTime": 219.649117, "createdAt": "2015-09-15T23:36:56.780000", "endpointUrl": "http://open.taobao.com", "apiName": "Taobao (cn)"}, {"responseTime": 120.423805, "createdAt": "2015-09-15T23:37:03.899000", "endpointUrl": "http://api.taobao.com", "apiName": "Taobao (cn)"}, {"responseTime": 90.188146, "createdAt": "2015-09-15T23:39:46.367000", "endpointUrl": "http://api.taobao.com", "apiName": "Taobao (cn)"}, {"responseTime": 89.34312, "createdAt": "2015-09-15T23:41:00.798000", "endpointUrl": "http://open.taobao.com", "apiName": "Taobao (cn)"}, {"responseTime": 204.218831, "createdAt": "2015-09-15T23:42:20.129000", "endpointUrl": "http://api.taobao.com", "apiName": "Taobao (cn)"}, {"responseTime": 91.943966, "createdAt": "2015-09-15T23:43:04.942000", "endpointUrl": "http://open.taobao.com", "apiName": "Taobao (cn)"}, {"responseTime": 65.939956, "createdAt": "2015-09-15T23:46:48.161000", "endpointUrl": "http://api.taobao.com", "apiName": "Taobao (cn)"}, {"responseTime": 83.346501, "createdAt": "2015-09-15T23:47:06.997000", "endpointUrl": "http://open.taobao.com", "apiName": "Taobao (cn)"}, {"responseTime": 78.961792, "createdAt": "2015-09-15T23:49:19.373000", "endpointUrl": "http://open.taobao.com", "apiName": "Taobao (cn)"}, {"responseTime": 133.159326, "createdAt": "2015-09-15T23:49:57.822000", "endpointUrl": "http://api.taobao.com", "apiName": "Taobao (cn)"}, {"responseTime": 122.263381, "createdAt": "2015-09-15T23:53:08.062000", "endpointUrl": "http://api.taobao.com", "apiName": "Taobao (cn)"}, {"responseTime": 95.109436, "createdAt": "2015-09-15T23:55:09.690000", "endpointUrl": "http://open.taobao.com", "apiName": "Taobao (cn)"}, {"responseTime": 101.905432, "createdAt": "2015-09-15T23:55:55.748000", "endpointUrl": "http://api.taobao.com", "apiName": "Taobao (cn)"}, {"responseTime": 73.310164, "createdAt": "2015-09-15T23:58:14.805000", "endpointUrl": "http://api.taobao.com", "apiName": "Taobao (cn)"}, {"responseTime": 76.654349, "createdAt": "2015-09-15T23:58:14.912000", "endpointUrl": "http://open.taobao.com", "apiName": "Taobao (cn)"}, {"responseTime": 93.33202, "createdAt": "2015-09-16T00:00:37.887000", "endpointUrl": "http://open.taobao.com", "apiName": "Taobao (cn)"}, {"responseTime": 117.850683, "createdAt": "2015-09-16T00:00:58.581000", "endpointUrl": "http://api.taobao.com", "apiName": "Taobao (cn)"}, {"responseTime": 155.620086, "createdAt": "2015-09-16T00:03:16.537000", "endpointUrl": "http://api.taobao.com", "apiName": "Taobao (cn)"}, {"responseTime": 99.346397, "createdAt": "2015-09-16T00:03:30.005000", "endpointUrl": "http://open.taobao.com", "apiName": "Taobao (cn)"}, {"responseTime": 119.704354, "createdAt": "2015-09-16T00:07:12.190000", "endpointUrl": "http://api.taobao.com", "apiName": "Taobao (cn)"}, {"responseTime": 86.939874, "createdAt": "2015-09-16T00:07:54.184000", "endpointUrl": "http://open.taobao.com", "apiName": "Taobao (cn)"}, {"responseTime": 67.186659, "createdAt": "2015-09-16T00:10:12.860000", "endpointUrl": "http://api.taobao.com", "apiName": "Taobao (cn)"}, {"responseTime": 82.199046, "createdAt": "2015-09-16T00:13:50.248000", "endpointUrl": "http://open.taobao.com", "apiName": "Taobao (cn)"}, {"responseTime": 144.740299, "createdAt": "2015-09-16T00:14:21.854000", "endpointUrl": "http://api.taobao.com", "apiName": "Taobao (cn)"}, {"responseTime": 119.285089, "createdAt": "2015-09-16T00:16:57.724000", "endpointUrl": "http://open.taobao.com", "apiName": "Taobao (cn)"}, {"responseTime": 77.045888, "createdAt": "2015-09-16T00:20:09.758000", "endpointUrl": "http://open.taobao.com", "apiName": "Taobao (cn)"}, {"responseTime": 102.126409, "createdAt": "2015-09-16T00:20:12.169000", "endpointUrl": "http://api.taobao.com", "apiName": "Taobao (cn)"}, {"responseTime": 85.944684, "createdAt": "2015-09-16T00:22:22.805000", "endpointUrl": "http://api.taobao.com", "apiName": "Taobao (cn)"}, {"responseTime": 76.990084, "createdAt": "2015-09-16T00:23:23.357000", "endpointUrl": "http://open.taobao.com", "apiName": "Taobao (cn)"}, {"responseTime": 90.111938, "createdAt": "2015-09-16T00:24:42.332000", "endpointUrl": "http://api.taobao.com", "apiName": "Taobao (cn)"}, {"responseTime": 76.507858, "createdAt": "2015-09-16T00:26:07.748000", "endpointUrl": "http://open.taobao.com", "apiName": "Taobao (cn)"}, {"responseTime": 73.878786, "createdAt": "2015-09-16T00:27:39.885000", "endpointUrl": "http://api.taobao.com", "apiName": "Taobao (cn)"}, {"responseTime": 92.086625, "createdAt": "2015-09-16T00:28:11.826000", "endpointUrl": "http://open.taobao.com", "apiName": "Taobao (cn)"}, {"responseTime": 141.344008, "createdAt": "2015-09-16T00:30:45.556000", "endpointUrl": "http://api.taobao.com", "apiName": "Taobao (cn)"}, {"responseTime": 122.979075, "createdAt": "2015-09-16T06:32:55.274000", "endpointUrl": "http://api.taobao.com", "apiName": "Taobao (cn)"}, {"responseTime": 83.418063, "createdAt": "2015-09-16T06:32:57.284000", "endpointUrl": "http://open.taobao.com", "apiName": "Taobao (cn)"}, {"responseTime": 101.584563, "createdAt": "2015-09-16T06:35:04.472000", "endpointUrl": "http://open.taobao.com", "apiName": "Taobao (cn)"}, {"responseTime": 73.484056, "createdAt": "2015-09-16T06:35:40.949000", "endpointUrl": "http://api.taobao.com", "apiName": "Taobao (cn)"}, {"responseTime": 80.511352, "createdAt": "2015-09-16T06:37:26.122000", "endpointUrl": "http://open.taobao.com", "apiName": "Taobao (cn)"}, {"responseTime": 125.911738, "createdAt": "2015-09-16T06:38:51.141000", "endpointUrl": "http://api.taobao.com", "apiName": "Taobao (cn)"}, {"responseTime": 82.572902, "createdAt": "2015-09-16T06:39:33.963000", "endpointUrl": "http://open.taobao.com", "apiName": "Taobao (cn)"}, {"responseTime": 118.087278, "createdAt": "2015-09-16T06:41:11.158000", "endpointUrl": "http://api.taobao.com", "apiName": "Taobao (cn)"}, {"responseTime": 120.874207, "createdAt": "2015-09-16T06:43:38.256000", "endpointUrl": "http://api.taobao.com", "apiName": "Taobao (cn)"}, {"responseTime": 85.149105, "createdAt": "2015-09-16T06:43:39.240000", "endpointUrl": "http://open.taobao.com", "apiName": "Taobao (cn)"}, {"responseTime": 95.265794, "createdAt": "2015-09-16T06:46:13.298000", "endpointUrl": "http://open.taobao.com", "apiName": "Taobao (cn)"}, {"responseTime": 118.850192, "createdAt": "2015-09-16T06:47:32.165000", "endpointUrl": "http://api.taobao.com", "apiName": "Taobao (cn)"}, {"responseTime": 76.134414, "createdAt": "2015-09-16T06:48:26.868000", "endpointUrl": "http://open.taobao.com", "apiName": "Taobao (cn)"}, {"responseTime": 86.585198, "createdAt": "2015-09-16T06:49:55.058000", "endpointUrl": "http://api.taobao.com", "apiName": "Taobao (cn)"}, {"responseTime": 84.759567, "createdAt": "2015-09-16T06:57:31.583000", "endpointUrl": "http://open.taobao.com", "apiName": "Taobao (cn)"}, {"responseTime": 92.579067, "createdAt": "2015-09-16T07:00:23.326000", "endpointUrl": "http://open.taobao.com", "apiName": "Taobao (cn)"}, {"responseTime": 102.443176, "createdAt": "2015-09-16T07:00:32.772000", "endpointUrl": "http://api.taobao.com", "apiName": "Taobao (cn)"}, {"responseTime": 95.808994, "createdAt": "2015-09-16T07:04:41.025000", "endpointUrl": "http://open.taobao.com", "apiName": "Taobao (cn)"}, {"responseTime": 143.161261, "createdAt": "2015-09-16T07:04:43.470000", "endpointUrl": "http://api.taobao.com", "apiName": "Taobao (cn)"}, {"responseTime": 132.55942, "createdAt": "2015-09-16T07:07:00.543000", "endpointUrl": "http://api.taobao.com", "apiName": "Taobao (cn)"}, {"responseTime": 80.588548, "createdAt": "2015-09-16T07:07:08.395000", "endpointUrl": "http://open.taobao.com", "apiName": "Taobao (cn)"}, {"responseTime": 73.283437, "createdAt": "2015-09-16T07:10:13.174000", "endpointUrl": "http://open.taobao.com", "apiName": "Taobao (cn)"}, {"responseTime": 71.039666, "createdAt": "2015-09-16T07:11:00.778000", "endpointUrl": "http://api.taobao.com", "apiName": "Taobao (cn)"}, {"responseTime": 94.047973, "createdAt": "2015-09-16T07:13:06.192000", "endpointUrl": "http://open.taobao.com", "apiName": "Taobao (cn)"}, {"responseTime": 115.124334, "createdAt": "2015-09-16T07:13:09.630000", "endpointUrl": "http://api.taobao.com", "apiName": "Taobao (cn)"}, {"responseTime": 113.174392, "createdAt": "2015-09-16T07:16:03.785000", "endpointUrl": "http://api.taobao.com", "apiName": "Taobao (cn)"}, {"responseTime": 115.922084, "createdAt": "2015-09-16T07:16:04.912000", "endpointUrl": "http://open.taobao.com", "apiName": "Taobao (cn)"}, {"responseTime": 185.650848, "createdAt": "2015-09-16T07:18:35.799000", "endpointUrl": "http://api.taobao.com", "apiName": "Taobao (cn)"}, {"responseTime": 92.148195, "createdAt": "2015-09-16T07:22:03.319000", "endpointUrl": "http://open.taobao.com", "apiName": "Taobao (cn)"}, {"responseTime": 89.753914, "createdAt": "2015-09-16T07:22:23.427000", "endpointUrl": "http://api.taobao.com", "apiName": "Taobao (cn)"}, {"responseTime": 94.107154, "createdAt": "2015-09-16T07:24:44.749000", "endpointUrl": "http://api.taobao.com", "apiName": "Taobao (cn)"}, {"responseTime": 89.295965, "createdAt": "2015-09-16T07:26:25.563000", "endpointUrl": "http://open.taobao.com", "apiName": "Taobao (cn)"}, {"responseTime": 86.84714, "createdAt": "2015-09-16T07:28:48.495000", "endpointUrl": "http://open.taobao.com", "apiName": "Taobao (cn)"}, {"responseTime": 113.604132, "createdAt": "2015-09-16T07:29:27.671000", "endpointUrl": "http://api.taobao.com", "apiName": "Taobao (cn)"}, {"responseTime": 164.063188, "createdAt": "2015-09-16T11:33:14.267000", "endpointUrl": "http://api.taobao.com", "apiName": "Taobao (cn)"}, {"responseTime": 93.491272, "createdAt": "2015-09-16T11:33:16.675000", "endpointUrl": "http://open.taobao.com", "apiName": "Taobao (cn)"}, {"responseTime": 90.180285, "createdAt": "2015-09-16T11:35:32.433000", "endpointUrl": "http://api.taobao.com", "apiName": "Taobao (cn)"}, {"responseTime": 88.590341, "createdAt": "2015-09-16T11:37:36.760000", "endpointUrl": "http://api.taobao.com", "apiName": "Taobao (cn)"}, {"responseTime": 112.7251, "createdAt": "2015-09-16T11:37:54.517000", "endpointUrl": "http://open.taobao.com", "apiName": "Taobao (cn)"}, {"responseTime": 167.647875, "createdAt": "2015-09-16T11:41:28.869000", "endpointUrl": "http://api.taobao.com", "apiName": "Taobao (cn)"}, {"responseTime": 79.84897, "createdAt": "2015-09-16T11:43:07.156000", "endpointUrl": "http://open.taobao.com", "apiName": "Taobao (cn)"}, {"responseTime": 74.061259, "createdAt": "2015-09-16T11:44:49.571000", "endpointUrl": "http://api.taobao.com", "apiName": "Taobao (cn)"}, {"responseTime": 78.309514, "createdAt": "2015-09-16T11:47:34.435000", "endpointUrl": "http://open.taobao.com", "apiName": "Taobao (cn)"}, {"responseTime": 109.132566, "createdAt": "2015-09-16T11:47:51.051000", "endpointUrl": "http://api.taobao.com", "apiName": "Taobao (cn)"}, {"responseTime": 74.657109, "createdAt": "2015-09-16T11:50:23.179000", "endpointUrl": "http://open.taobao.com", "apiName": "Taobao (cn)"}, {"responseTime": 83.659992, "createdAt": "2015-09-16T11:51:12.243000", "endpointUrl": "http://api.taobao.com", "apiName": "Taobao (cn)"}, {"responseTime": 77.684898, "createdAt": "2015-09-16T11:52:50.236000", "endpointUrl": "http://open.taobao.com", "apiName": "Taobao (cn)"}, {"responseTime": 115.627784, "createdAt": "2015-09-16T11:53:30.054000", "endpointUrl": "http://api.taobao.com", "apiName": "Taobao (cn)"}, {"responseTime": 110.675162, "createdAt": "2015-09-16T11:59:30.710000", "endpointUrl": "http://api.taobao.com", "apiName": "Taobao (cn)"}, {"responseTime": 80.394146, "createdAt": "2015-09-16T12:02:17.533000", "endpointUrl": "http://open.taobao.com", "apiName": "Taobao (cn)"}, {"responseTime": 84.307068, "createdAt": "2015-09-16T12:04:30.141000", "endpointUrl": "http://open.taobao.com", "apiName": "Taobao (cn)"}, {"responseTime": 139.273667, "createdAt": "2015-09-16T12:04:46.220000", "endpointUrl": "http://api.taobao.com", "apiName": "Taobao (cn)"}, {"responseTime": 91.682075, "createdAt": "2015-09-16T12:08:41.893000", "endpointUrl": "http://open.taobao.com", "apiName": "Taobao (cn)"}, {"responseTime": 82.454903, "createdAt": "2015-09-16T12:10:48.519000", "endpointUrl": "http://open.taobao.com", "apiName": "Taobao (cn)"}, {"responseTime": 94.427436, "createdAt": "2015-09-16T12:17:26.671000", "endpointUrl": "http://open.taobao.com", "apiName": "Taobao (cn)"}, {"responseTime": 225.431797, "createdAt": "2015-09-16T12:18:35.235000", "endpointUrl": "http://api.taobao.com", "apiName": "Taobao (cn)"}, {"responseTime": 86.797568, "createdAt": "2015-09-16T12:21:28.933000", "endpointUrl": "http://api.taobao.com", "apiName": "Taobao (cn)"}, {"responseTime": 73.661895, "createdAt": "2015-09-16T12:22:13.739000", "endpointUrl": "http://open.taobao.com", "apiName": "Taobao (cn)"}, {"responseTime": 76.835891, "createdAt": "2015-09-16T12:25:23.466000", "endpointUrl": "http://open.taobao.com", "apiName": "Taobao (cn)"}, {"responseTime": 205.507392, "createdAt": "2015-09-16T12:27:19.648000", "endpointUrl": "http://api.taobao.com", "apiName": "Taobao (cn)"}, {"responseTime": 101.498884, "createdAt": "2015-09-16T12:27:45.371000", "endpointUrl": "http://open.taobao.com", "apiName": "Taobao (cn)"}, {"responseTime": 77.071539, "createdAt": "2015-09-16T12:30:25.324000", "endpointUrl": "http://open.taobao.com", "apiName": "Taobao (cn)"}, {"responseTime": 67.075984, "createdAt": "2015-09-16T12:30:41.689000", "endpointUrl": "http://api.taobao.com", "apiName": "Taobao (cn)"}, {"responseTime": 148.389492, "createdAt": "2015-09-16T23:32:19.517000", "endpointUrl": "http://api.taobao.com", "apiName": "Taobao (cn)"}, {"responseTime": 76.501041, "createdAt": "2015-09-16T23:34:24.855000", "endpointUrl": "http://open.taobao.com", "apiName": "Taobao (cn)"}, {"responseTime": 150.771453, "createdAt": "2015-09-16T23:37:27.753000", "endpointUrl": "http://api.taobao.com", "apiName": "Taobao (cn)"}, {"responseTime": 83.167597, "createdAt": "2015-09-16T23:40:03.085000", "endpointUrl": "http://api.taobao.com", "apiName": "Taobao (cn)"}, {"responseTime": 98.681738, "createdAt": "2015-09-16T23:40:19.768000", "endpointUrl": "http://open.taobao.com", "apiName": "Taobao (cn)"}, {"responseTime": 79.480678, "createdAt": "2015-09-16T23:43:44.834000", "endpointUrl": "http://open.taobao.com", "apiName": "Taobao (cn)"}, {"responseTime": 75.585497, "createdAt": "2015-09-16T23:46:57.955000", "endpointUrl": "http://open.taobao.com", "apiName": "Taobao (cn)"}, {"responseTime": 117.595551, "createdAt": "2015-09-16T23:46:59.060000", "endpointUrl": "http://api.taobao.com", "apiName": "Taobao (cn)"}, {"responseTime": 84.935435, "createdAt": "2015-09-16T23:49:43.913000", "endpointUrl": "http://open.taobao.com", "apiName": "Taobao (cn)"}, {"responseTime": 73.359642, "createdAt": "2015-09-16T23:51:25.631000", "endpointUrl": "http://api.taobao.com", "apiName": "Taobao (cn)"}, {"responseTime": 91.369855, "createdAt": "2015-09-16T23:54:46.025000", "endpointUrl": "http://open.taobao.com", "apiName": "Taobao (cn)"}, {"responseTime": 75.961167, "createdAt": "2015-09-16T23:56:50.774000", "endpointUrl": "http://api.taobao.com", "apiName": "Taobao (cn)"}, {"responseTime": 83.643912, "createdAt": "2015-09-17T00:01:54.307000", "endpointUrl": "http://open.taobao.com", "apiName": "Taobao (cn)"}, {"responseTime": 163.503899, "createdAt": "2015-09-17T00:03:57.271000", "endpointUrl": "http://api.taobao.com", "apiName": "Taobao (cn)"}, {"responseTime": 85.397906, "createdAt": "2015-09-17T00:04:25.962000", "endpointUrl": "http://open.taobao.com", "apiName": "Taobao (cn)"}, {"responseTime": 66.797483, "createdAt": "2015-09-17T00:06:18.504000", "endpointUrl": "http://api.taobao.com", "apiName": "Taobao (cn)"}, {"responseTime": 79.485126, "createdAt": "2015-09-17T00:07:02.777000", "endpointUrl": "http://open.taobao.com", "apiName": "Taobao (cn)"}, {"responseTime": 121.242864, "createdAt": "2015-09-17T00:09:04.191000", "endpointUrl": "http://api.taobao.com", "apiName": "Taobao (cn)"}, {"responseTime": 88.942822, "createdAt": "2015-09-17T00:10:04.956000", "endpointUrl": "http://open.taobao.com", "apiName": "Taobao (cn)"}, {"responseTime": 85.673559, "createdAt": "2015-09-17T00:11:26.784000", "endpointUrl": "http://api.taobao.com", "apiName": "Taobao (cn)"}, {"responseTime": 76.919476, "createdAt": "2015-09-17T00:12:26.897000", "endpointUrl": "http://open.taobao.com", "apiName": "Taobao (cn)"}, {"responseTime": 186.111365, "createdAt": "2015-09-17T00:15:56.928000", "endpointUrl": "http://api.taobao.com", "apiName": "Taobao (cn)"}, {"responseTime": 85.60532, "createdAt": "2015-09-17T00:19:20.858000", "endpointUrl": "http://open.taobao.com", "apiName": "Taobao (cn)"}, {"responseTime": 87.676601, "createdAt": "2015-09-17T00:21:06.135000", "endpointUrl": "http://api.taobao.com", "apiName": "Taobao (cn)"}, {"responseTime": 69.695229, "createdAt": "2015-09-17T00:24:14.604000", "endpointUrl": "http://api.taobao.com", "apiName": "Taobao (cn)"}, {"responseTime": 76.916689, "createdAt": "2015-09-17T00:24:28.934000", "endpointUrl": "http://open.taobao.com", "apiName": "Taobao (cn)"}, {"responseTime": 108.003689, "createdAt": "2015-09-17T00:26:42.315000", "endpointUrl": "http://open.taobao.com", "apiName": "Taobao (cn)"}, {"responseTime": 143.764141, "createdAt": "2015-09-17T00:27:54.583000", "endpointUrl": "http://api.taobao.com", "apiName": "Taobao (cn)"}, {"responseTime": 95.089473, "createdAt": "2015-09-17T00:29:00.707000", "endpointUrl": "http://open.taobao.com", "apiName": "Taobao (cn)"}, {"responseTime": 87.002781, "createdAt": "2015-09-17T00:31:11.310000", "endpointUrl": "http://api.taobao.com", "apiName": "Taobao (cn)"}, {"responseTime": 172.141903, "createdAt": "2015-09-17T06:32:57.688000", "endpointUrl": "http://api.taobao.com", "apiName": "Taobao (cn)"}, {"responseTime": 81.8767, "createdAt": "2015-09-17T06:33:46.188000", "endpointUrl": "http://open.taobao.com", "apiName": "Taobao (cn)"}, {"responseTime": 84.744757, "createdAt": "2015-09-17T06:34:59.074000", "endpointUrl": "http://api.taobao.com", "apiName": "Taobao (cn)"}, {"responseTime": 87.911076, "createdAt": "2015-09-17T06:36:41.414000", "endpointUrl": "http://open.taobao.com", "apiName": "Taobao (cn)"}, {"responseTime": 70.750311, "createdAt": "2015-09-17T06:37:04.150000", "endpointUrl": "http://api.taobao.com", "apiName": "Taobao (cn)"}, {"responseTime": 123.990253, "createdAt": "2015-09-17T06:39:13.538000", "endpointUrl": "http://api.taobao.com", "apiName": "Taobao (cn)"}, {"responseTime": 74.536165, "createdAt": "2015-09-17T06:39:23.067000", "endpointUrl": "http://open.taobao.com", "apiName": "Taobao (cn)"}, {"responseTime": 79.70082, "createdAt": "2015-09-17T06:43:29.535000", "endpointUrl": "http://open.taobao.com", "apiName": "Taobao (cn)"}, {"responseTime": 121.674599, "createdAt": "2015-09-17T06:43:37.189000", "endpointUrl": "http://api.taobao.com", "apiName": "Taobao (cn)"}, {"responseTime": 129.413179, "createdAt": "2015-09-17T06:47:03.439000", "endpointUrl": "http://api.taobao.com", "apiName": "Taobao (cn)"}, {"responseTime": 86.022716, "createdAt": "2015-09-17T06:47:59.016000", "endpointUrl": "http://open.taobao.com", "apiName": "Taobao (cn)"}, {"responseTime": 72.706812, "createdAt": "2015-09-17T06:49:03.757000", "endpointUrl": "http://api.taobao.com", "apiName": "Taobao (cn)"}, {"responseTime": 66.099127, "createdAt": "2015-09-17T06:51:16.985000", "endpointUrl": "http://api.taobao.com", "apiName": "Taobao (cn)"}, {"responseTime": 79.017895, "createdAt": "2015-09-17T06:53:27.518000", "endpointUrl": "http://open.taobao.com", "apiName": "Taobao (cn)"}, {"responseTime": 113.096985, "createdAt": "2015-09-17T06:54:29.630000", "endpointUrl": "http://api.taobao.com", "apiName": "Taobao (cn)"}, {"responseTime": 79.725785, "createdAt": "2015-09-17T06:55:44.748000", "endpointUrl": "http://open.taobao.com", "apiName": "Taobao (cn)"}, {"responseTime": 74.600522, "createdAt": "2015-09-17T06:57:49.165000", "endpointUrl": "http://open.taobao.com", "apiName": "Taobao (cn)"}, {"responseTime": 83.384815, "createdAt": "2015-09-17T07:00:38.907000", "endpointUrl": "http://open.taobao.com", "apiName": "Taobao (cn)"}, {"responseTime": 5111.987104, "createdAt": "2015-09-17T07:04:15.918000", "endpointUrl": "http://api.taobao.com", "apiName": "Taobao (cn)"}, {"responseTime": 94.382071, "createdAt": "2015-09-17T07:05:12.298000", "endpointUrl": "http://open.taobao.com", "apiName": "Taobao (cn)"}, {"responseTime": 81.713693, "createdAt": "2015-09-17T07:07:20.121000", "endpointUrl": "http://open.taobao.com", "apiName": "Taobao (cn)"}, {"responseTime": 113.264046, "createdAt": "2015-09-17T07:09:49.981000", "endpointUrl": "http://api.taobao.com", "apiName": "Taobao (cn)"}, {"responseTime": 74.390818, "createdAt": "2015-09-17T07:12:00.293000", "endpointUrl": "http://api.taobao.com", "apiName": "Taobao (cn)"}, {"responseTime": 75.553884, "createdAt": "2015-09-17T07:13:11.056000", "endpointUrl": "http://open.taobao.com", "apiName": "Taobao (cn)"}, {"responseTime": 84.067938, "createdAt": "2015-09-17T07:16:10.643000", "endpointUrl": "http://open.taobao.com", "apiName": "Taobao (cn)"}, {"responseTime": 72.809151, "createdAt": "2015-09-17T07:18:16.083000", "endpointUrl": "http://open.taobao.com", "apiName": "Taobao (cn)"}, {"responseTime": 148.50209, "createdAt": "2015-09-17T07:19:59.882000", "endpointUrl": "http://api.taobao.com", "apiName": "Taobao (cn)"}, {"responseTime": 298.59103, "createdAt": "2015-09-17T07:23:52.358000", "endpointUrl": "http://open.taobao.com", "apiName": "Taobao (cn)"}, {"responseTime": 139.547168, "createdAt": "2015-09-17T07:25:18.846000", "endpointUrl": "http://api.taobao.com", "apiName": "Taobao (cn)"}, {"responseTime": 69.669794, "createdAt": "2015-09-17T07:29:53.164000", "endpointUrl": "http://api.taobao.com", "apiName": "Taobao (cn)"}, {"responseTime": 87.356922, "createdAt": "2015-09-17T07:30:41.163000", "endpointUrl": "http://open.taobao.com", "apiName": "Taobao (cn)"}, {"responseTime": 131.18459, "createdAt": "2015-09-17T11:34:57.178000", "endpointUrl": "http://api.taobao.com", "apiName": "Taobao (cn)"}, {"responseTime": 98.147357, "createdAt": "2015-09-17T11:35:32.239000", "endpointUrl": "http://open.taobao.com", "apiName": "Taobao (cn)"}, {"responseTime": 70.160829, "createdAt": "2015-09-17T11:37:26.348000", "endpointUrl": "http://api.taobao.com", "apiName": "Taobao (cn)"}, {"responseTime": 120.002773, "createdAt": "2015-09-17T11:39:28.413000", "endpointUrl": "http://api.taobao.com", "apiName": "Taobao (cn)"}, {"responseTime": 133.801548, "createdAt": "2015-09-17T11:41:43.647000", "endpointUrl": "http://api.taobao.com", "apiName": "Taobao (cn)"}, {"responseTime": 86.042752, "createdAt": "2015-09-17T11:45:29.086000", "endpointUrl": "http://open.taobao.com", "apiName": "Taobao (cn)"}, {"responseTime": 69.280014, "createdAt": "2015-09-17T11:45:29.395000", "endpointUrl": "http://api.taobao.com", "apiName": "Taobao (cn)"}, {"responseTime": 144.187989, "createdAt": "2015-09-17T11:51:00.380000", "endpointUrl": "http://api.taobao.com", "apiName": "Taobao (cn)"}, {"responseTime": 89.553725, "createdAt": "2015-09-17T11:51:01.584000", "endpointUrl": "http://open.taobao.com", "apiName": "Taobao (cn)"}, {"responseTime": 70.810783, "createdAt": "2015-09-17T11:55:18.089000", "endpointUrl": "http://api.taobao.com", "apiName": "Taobao (cn)"}, {"responseTime": 91.977382, "createdAt": "2015-09-17T11:55:20.892000", "endpointUrl": "http://open.taobao.com", "apiName": "Taobao (cn)"}, {"responseTime": 105.363395, "createdAt": "2015-09-17T11:57:24.720000", "endpointUrl": "http://api.taobao.com", "apiName": "Taobao (cn)"}, {"responseTime": 78.089884, "createdAt": "2015-09-17T11:58:26.481000", "endpointUrl": "http://open.taobao.com", "apiName": "Taobao (cn)"}, {"responseTime": 86.176025, "createdAt": "2015-09-17T12:00:43.030000", "endpointUrl": "http://api.taobao.com", "apiName": "Taobao (cn)"}, {"responseTime": 84.204702, "createdAt": "2015-09-17T12:03:02.788000", "endpointUrl": "http://open.taobao.com", "apiName": "Taobao (cn)"}, {"responseTime": 138.796678, "createdAt": "2015-09-17T12:04:06.362000", "endpointUrl": "http://api.taobao.com", "apiName": "Taobao (cn)"}, {"responseTime": 78.312922, "createdAt": "2015-09-17T12:06:51.466000", "endpointUrl": "http://open.taobao.com", "apiName": "Taobao (cn)"}, {"responseTime": 83.107303, "createdAt": "2015-09-17T12:07:05.347000", "endpointUrl": "http://api.taobao.com", "apiName": "Taobao (cn)"}, {"responseTime": 101.36742, "createdAt": "2015-09-17T12:09:16.513000", "endpointUrl": "http://open.taobao.com", "apiName": "Taobao (cn)"}, {"responseTime": 93.334276, "createdAt": "2015-09-17T12:09:27.713000", "endpointUrl": "http://api.taobao.com", "apiName": "Taobao (cn)"}, {"responseTime": 84.893394, "createdAt": "2015-09-17T12:11:44.058000", "endpointUrl": "http://api.taobao.com", "apiName": "Taobao (cn)"}, {"responseTime": 92.358804, "createdAt": "2015-09-17T12:11:51.028000", "endpointUrl": "http://open.taobao.com", "apiName": "Taobao (cn)"}, {"responseTime": 97.248595, "createdAt": "2015-09-17T12:14:01.522000", "endpointUrl": "http://open.taobao.com", "apiName": "Taobao (cn)"}, {"responseTime": 125.269548, "createdAt": "2015-09-17T12:15:33.939000", "endpointUrl": "http://api.taobao.com", "apiName": "Taobao (cn)"}, {"responseTime": 91.529827, "createdAt": "2015-09-17T12:16:38.602000", "endpointUrl": "http://open.taobao.com", "apiName": "Taobao (cn)"}, {"responseTime": 65.786897, "createdAt": "2015-09-17T12:18:14.847000", "endpointUrl": "http://api.taobao.com", "apiName": "Taobao (cn)"}, {"responseTime": 84.212091, "createdAt": "2015-09-17T12:20:58.653000", "endpointUrl": "http://api.taobao.com", "apiName": "Taobao (cn)"}, {"responseTime": 92.097033, "createdAt": "2015-09-17T12:23:35.097000", "endpointUrl": "http://open.taobao.com", "apiName": "Taobao (cn)"}, {"responseTime": 80.191763, "createdAt": "2015-09-17T12:24:27.970000", "endpointUrl": "http://api.taobao.com", "apiName": "Taobao (cn)"}, {"responseTime": 141.646822, "createdAt": "2015-09-17T12:27:42.486000", "endpointUrl": "http://api.taobao.com", "apiName": "Taobao (cn)"}, {"responseTime": 77.803998, "createdAt": "2015-09-17T12:27:48.531000", "endpointUrl": "http://open.taobao.com", "apiName": "Taobao (cn)"}, {"responseTime": 81.254661, "createdAt": "2015-09-17T12:30:07.351000", "endpointUrl": "http://open.taobao.com", "apiName": "Taobao (cn)"}, {"responseTime": 79.297186, "createdAt": "2015-09-17T12:31:13.064000", "endpointUrl": "http://api.taobao.com", "apiName": "Taobao (cn)"}]